{
	"1": {
		"keeper_Player": "Oliver Baumann\\Oliver-Baumann",
		"keeper_Nation": "de GER",
		"keeper_Pos": "GK",
		"keeper_Squad": "Hoffenheim",
		"keeper_Age": "30-152",
		"keeper_Born": 1990,
		"keeper_MP": 4,
		"keeper_Starts": 4,
		"keeper_Min": 360,
		"keeper_GA": 6,
		"keeper_GA90": 1.5,
		"keeper_SoTA": 19,
		"keeper_Saves": 11,
		"keeper_Save%": ".684",
		"keeper_W": 2,
		"keeper_D": 0,
		"keeper_L": 2,
		"keeper_CS": 0,
		"keeper_CS%": 0,
		"keeper_PKatt": 0,
		"keeper_PKA": 0,
		"keeper_PKsv": 0,
		"keeper_PKm": 0,
		"keeper_Matches": "Matches",
		"code": "47064058",
		"url": "/en/players/47064058/Oliver-Baumann",
		"keeper_adv_Player": "Oliver Baumann\\Oliver-Baumann",
		"keeper_adv_Nation": "de GER",
		"keeper_adv_Pos": "GK",
		"keeper_adv_Squad": "Hoffenheim",
		"keeper_adv_Age": "30-152",
		"keeper_adv_Born": 1990,
		"keeper_adv_90s": 4,
		"keeper_adv_GA": 6,
		"keeper_adv_PKA": 0,
		"keeper_adv_FK": 0,
		"keeper_adv_CK": 0,
		"keeper_adv_OG": 0,
		"keeper_adv_PSxG": 6.2,
		"keeper_adv_PSxG/SoT": 0.33,
		"keeper_adv_PSxG+/-": "+0.2",
		"keeper_adv_/90": "+0.06",
		"keeper_adv_Cmp": 26,
		"keeper_adv_Att": 88,
		"keeper_adv_Cmp%": 29.5,
		"keeper_adv_Att__1": 153,
		"keeper_adv_Thr": 21,
		"keeper_adv_Launch%": 41.8,
		"keeper_adv_AvgLen": 37.5,
		"keeper_adv_Att__2": 48,
		"keeper_adv_Launch%__1": 50,
		"keeper_adv_AvgLen__1": 42.6,
		"keeper_adv_Opp": 44,
		"keeper_adv_Stp": 1,
		"keeper_adv_Stp%": 2.3,
		"keeper_adv_#OPA": 6,
		"keeper_adv_#OPA/90": 1.5,
		"keeper_adv_AvgDist": 15.8,
		"keeper_adv_Matches": "Matches"
	},
	"2": {
		"keeper_Player": "Roman Bürki\\Roman-Burki",
		"keeper_Nation": "ch SUI",
		"keeper_Pos": "GK",
		"keeper_Squad": "Dortmund",
		"keeper_Age": "29-353",
		"keeper_Born": 1990,
		"keeper_MP": 4,
		"keeper_Starts": 4,
		"keeper_Min": 360,
		"keeper_GA": 2,
		"keeper_GA90": 0.5,
		"keeper_SoTA": 8,
		"keeper_Saves": 6,
		"keeper_Save%": ".750",
		"keeper_W": 3,
		"keeper_D": 0,
		"keeper_L": 1,
		"keeper_CS": 3,
		"keeper_CS%": 75,
		"keeper_PKatt": 0,
		"keeper_PKA": 0,
		"keeper_PKsv": 0,
		"keeper_PKm": 0,
		"keeper_Matches": "Matches",
		"code": "9d12e142",
		"url": "/en/players/9d12e142/Roman-Burki",
		"keeper_adv_Player": "Roman Bürki\\Roman-Burki",
		"keeper_adv_Nation": "ch SUI",
		"keeper_adv_Pos": "GK",
		"keeper_adv_Squad": "Dortmund",
		"keeper_adv_Age": "29-353",
		"keeper_adv_Born": 1990,
		"keeper_adv_90s": 4,
		"keeper_adv_GA": 2,
		"keeper_adv_PKA": 0,
		"keeper_adv_FK": 0,
		"keeper_adv_CK": 0,
		"keeper_adv_OG": 0,
		"keeper_adv_PSxG": 1.9,
		"keeper_adv_PSxG/SoT": 0.32,
		"keeper_adv_PSxG+/-": -0.1,
		"keeper_adv_/90": -0.04,
		"keeper_adv_Cmp": 7,
		"keeper_adv_Att": 21,
		"keeper_adv_Cmp%": 33.3,
		"keeper_adv_Att__1": 70,
		"keeper_adv_Thr": 11,
		"keeper_adv_Launch%": 27.1,
		"keeper_adv_AvgLen": 30.7,
		"keeper_adv_Att__2": 13,
		"keeper_adv_Launch%__1": 15.4,
		"keeper_adv_AvgLen__1": 28.2,
		"keeper_adv_Opp": 12,
		"keeper_adv_Stp": 0,
		"keeper_adv_Stp%": 0,
		"keeper_adv_#OPA": 0,
		"keeper_adv_#OPA/90": 0,
		"keeper_adv_AvgDist": 14.1,
		"keeper_adv_Matches": "Matches"
	},
	"3": {
		"keeper_Player": "Koen Casteels\\Koen-Casteels",
		"keeper_Nation": "be BEL",
		"keeper_Pos": "GK",
		"keeper_Squad": "Wolfsburg",
		"keeper_Age": "28-129",
		"keeper_Born": 1992,
		"keeper_MP": 4,
		"keeper_Starts": 4,
		"keeper_Min": 360,
		"keeper_GA": 2,
		"keeper_GA90": 0.5,
		"keeper_SoTA": 6,
		"keeper_Saves": 5,
		"keeper_Save%": ".833",
		"keeper_W": 1,
		"keeper_D": 3,
		"keeper_L": 0,
		"keeper_CS": 2,
		"keeper_CS%": 50,
		"keeper_PKatt": 1,
		"keeper_PKA": 1,
		"keeper_PKsv": 0,
		"keeper_PKm": 0,
		"keeper_Matches": "Matches",
		"code": "db401046",
		"url": "/en/players/db401046/Koen-Casteels",
		"keeper_adv_Player": "Koen Casteels\\Koen-Casteels",
		"keeper_adv_Nation": "be BEL",
		"keeper_adv_Pos": "GK",
		"keeper_adv_Squad": "Wolfsburg",
		"keeper_adv_Age": "28-129",
		"keeper_adv_Born": 1992,
		"keeper_adv_90s": 4,
		"keeper_adv_GA": 2,
		"keeper_adv_PKA": 1,
		"keeper_adv_FK": 0,
		"keeper_adv_CK": 0,
		"keeper_adv_OG": 0,
		"keeper_adv_PSxG": 1.7,
		"keeper_adv_PSxG/SoT": 0.22,
		"keeper_adv_PSxG+/-": -0.3,
		"keeper_adv_/90": -0.06,
		"keeper_adv_Cmp": 34,
		"keeper_adv_Att": 81,
		"keeper_adv_Cmp%": 42,
		"keeper_adv_Att__1": 143,
		"keeper_adv_Thr": 21,
		"keeper_adv_Launch%": 44.1,
		"keeper_adv_AvgLen": 38.9,
		"keeper_adv_Att__2": 23,
		"keeper_adv_Launch%__1": 78.3,
		"keeper_adv_AvgLen__1": 55.7,
		"keeper_adv_Opp": 34,
		"keeper_adv_Stp": 5,
		"keeper_adv_Stp%": 14.7,
		"keeper_adv_#OPA": 1,
		"keeper_adv_#OPA/90": 0.25,
		"keeper_adv_AvgDist": 14.5,
		"keeper_adv_Matches": "Matches"
	},
	"4": {
		"keeper_Player": "Ralf Fährmann\\Ralf-Fahrmann",
		"keeper_Nation": "de GER",
		"keeper_Pos": "GK",
		"keeper_Squad": "Schalke 04",
		"keeper_Age": "32-035",
		"keeper_Born": 1988,
		"keeper_MP": 3,
		"keeper_Starts": 3,
		"keeper_Min": 225,
		"keeper_GA": 14,
		"keeper_GA90": 5.6,
		"keeper_SoTA": 18,
		"keeper_Saves": 7,
		"keeper_Save%": ".333",
		"keeper_W": 0,
		"keeper_D": 0,
		"keeper_L": 3,
		"keeper_CS": 0,
		"keeper_CS%": 0,
		"keeper_PKatt": 2,
		"keeper_PKA": 2,
		"keeper_PKsv": 0,
		"keeper_PKm": 0,
		"keeper_Matches": "Matches",
		"code": "1e43fad8",
		"url": "/en/players/1e43fad8/Ralf-Fahrmann",
		"keeper_adv_Player": "Ralf Fährmann\\Ralf-Fahrmann",
		"keeper_adv_Nation": "de GER",
		"keeper_adv_Pos": "GK",
		"keeper_adv_Squad": "Schalke 04",
		"keeper_adv_Age": "32-035",
		"keeper_adv_Born": 1988,
		"keeper_adv_90s": 2.5,
		"keeper_adv_GA": 14,
		"keeper_adv_PKA": 2,
		"keeper_adv_FK": 0,
		"keeper_adv_CK": 2,
		"keeper_adv_OG": 1,
		"keeper_adv_PSxG": 9.3,
		"keeper_adv_PSxG/SoT": 0.43,
		"keeper_adv_PSxG+/-": -3.7,
		"keeper_adv_/90": -1.46,
		"keeper_adv_Cmp": 17,
		"keeper_adv_Att": 50,
		"keeper_adv_Cmp%": 34,
		"keeper_adv_Att__1": 82,
		"keeper_adv_Thr": 14,
		"keeper_adv_Launch%": 45.1,
		"keeper_adv_AvgLen": 37.6,
		"keeper_adv_Att__2": 24,
		"keeper_adv_Launch%__1": 54.2,
		"keeper_adv_AvgLen__1": 42,
		"keeper_adv_Opp": 23,
		"keeper_adv_Stp": 0,
		"keeper_adv_Stp%": 0,
		"keeper_adv_#OPA": 5,
		"keeper_adv_#OPA/90": 2,
		"keeper_adv_AvgDist": 15.1,
		"keeper_adv_Matches": "Matches"
	},
	"5": {
		"keeper_Player": "Rafał Gikiewicz\\Rafal-Gikiewicz",
		"keeper_Nation": "pl POL",
		"keeper_Pos": "GK",
		"keeper_Squad": "Augsburg",
		"keeper_Age": "33-006",
		"keeper_Born": 1987,
		"keeper_MP": 6,
		"keeper_Starts": 6,
		"keeper_Min": 540,
		"keeper_GA": 8,
		"keeper_GA90": 1.33,
		"keeper_SoTA": 30,
		"keeper_Saves": 23,
		"keeper_Save%": ".767",
		"keeper_W": 3,
		"keeper_D": 1,
		"keeper_L": 2,
		"keeper_CS": 2,
		"keeper_CS%": 33.3,
		"keeper_PKatt": 1,
		"keeper_PKA": 1,
		"keeper_PKsv": 0,
		"keeper_PKm": 0,
		"keeper_Matches": "Matches",
		"code": "17376543",
		"url": "/en/players/17376543/Rafal-Gikiewicz",
		"keeper_adv_Player": "Rafał Gikiewicz\\Rafal-Gikiewicz",
		"keeper_adv_Nation": "pl POL",
		"keeper_adv_Pos": "GK",
		"keeper_adv_Squad": "Augsburg",
		"keeper_adv_Age": "33-006",
		"keeper_adv_Born": 1987,
		"keeper_adv_90s": 6,
		"keeper_adv_GA": 8,
		"keeper_adv_PKA": 1,
		"keeper_adv_FK": 0,
		"keeper_adv_CK": 0,
		"keeper_adv_OG": 0,
		"keeper_adv_PSxG": 8.6,
		"keeper_adv_PSxG/SoT": 0.3,
		"keeper_adv_PSxG+/-": "+2.6",
		"keeper_adv_/90": "+0.51",
		"keeper_adv_Cmp": 33,
		"keeper_adv_Att": 95,
		"keeper_adv_Cmp%": 34.7,
		"keeper_adv_Att__1": 158,
		"keeper_adv_Thr": 34,
		"keeper_adv_Launch%": 43.7,
		"keeper_adv_AvgLen": 38.3,
		"keeper_adv_Att__2": 41,
		"keeper_adv_Launch%__1": 63.4,
		"keeper_adv_AvgLen__1": 52.2,
		"keeper_adv_Opp": 64,
		"keeper_adv_Stp": 5,
		"keeper_adv_Stp%": 7.8,
		"keeper_adv_#OPA": 5,
		"keeper_adv_#OPA/90": 1,
		"keeper_adv_AvgDist": 14.4,
		"keeper_adv_Matches": "Matches"
	},
	"6": {
		"keeper_Player": "Péter Gulácsi\\Peter-Gulacsi",
		"keeper_Nation": "hu HUN",
		"keeper_Pos": "GK",
		"keeper_Squad": "RB Leipzig",
		"keeper_Age": "30-179",
		"keeper_Born": 1990,
		"keeper_MP": 6,
		"keeper_Starts": 6,
		"keeper_Min": 540,
		"keeper_GA": 4,
		"keeper_GA90": 0.67,
		"keeper_SoTA": 13,
		"keeper_Saves": 9,
		"keeper_Save%": ".692",
		"keeper_W": 4,
		"keeper_D": 1,
		"keeper_L": 1,
		"keeper_CS": 2,
		"keeper_CS%": 33.3,
		"keeper_PKatt": 0,
		"keeper_PKA": 0,
		"keeper_PKsv": 0,
		"keeper_PKm": 0,
		"keeper_Matches": "Matches",
		"code": "bcb2ccd8",
		"url": "/en/players/bcb2ccd8/Peter-Gulacsi",
		"keeper_adv_Player": "Péter Gulácsi\\Peter-Gulacsi",
		"keeper_adv_Nation": "hu HUN",
		"keeper_adv_Pos": "GK",
		"keeper_adv_Squad": "RB Leipzig",
		"keeper_adv_Age": "30-179",
		"keeper_adv_Born": 1990,
		"keeper_adv_90s": 6,
		"keeper_adv_GA": 4,
		"keeper_adv_PKA": 0,
		"keeper_adv_FK": 0,
		"keeper_adv_CK": 0,
		"keeper_adv_OG": 0,
		"keeper_adv_PSxG": 2.5,
		"keeper_adv_PSxG/SoT": 0.25,
		"keeper_adv_PSxG+/-": -0.5,
		"keeper_adv_/90": -0.09,
		"keeper_adv_Cmp": 20,
		"keeper_adv_Att": 35,
		"keeper_adv_Cmp%": 57.1,
		"keeper_adv_Att__1": 135,
		"keeper_adv_Thr": 17,
		"keeper_adv_Launch%": 22.2,
		"keeper_adv_AvgLen": 30.1,
		"keeper_adv_Att__2": 26,
		"keeper_adv_Launch%__1": 19.2,
		"keeper_adv_AvgLen__1": 28.2,
		"keeper_adv_Opp": 24,
		"keeper_adv_Stp": 1,
		"keeper_adv_Stp%": 4.2,
		"keeper_adv_#OPA": 6,
		"keeper_adv_#OPA/90": 1.2,
		"keeper_adv_AvgDist": 17,
		"keeper_adv_Matches": "Matches"
	},
	"7": {
		"keeper_Player": "Marwin Hitz\\Marwin-Hitz",
		"keeper_Nation": "ch SUI",
		"keeper_Pos": "GK",
		"keeper_Squad": "Dortmund",
		"keeper_Age": "33-044",
		"keeper_Born": 1987,
		"keeper_MP": 2,
		"keeper_Starts": 2,
		"keeper_Min": 180,
		"keeper_GA": 0,
		"keeper_GA90": 0,
		"keeper_SoTA": 5,
		"keeper_Saves": 5,
		"keeper_Save%": 1,
		"keeper_W": 2,
		"keeper_D": 0,
		"keeper_L": 0,
		"keeper_CS": 2,
		"keeper_CS%": 100,
		"keeper_PKatt": 0,
		"keeper_PKA": 0,
		"keeper_PKsv": 0,
		"keeper_PKm": 0,
		"keeper_Matches": "Matches",
		"code": "2e7ff968",
		"url": "/en/players/2e7ff968/Marwin-Hitz",
		"keeper_adv_Player": "Marwin Hitz\\Marwin-Hitz",
		"keeper_adv_Nation": "ch SUI",
		"keeper_adv_Pos": "GK",
		"keeper_adv_Squad": "Dortmund",
		"keeper_adv_Age": "33-044",
		"keeper_adv_Born": 1987,
		"keeper_adv_90s": 2,
		"keeper_adv_GA": 0,
		"keeper_adv_PKA": 0,
		"keeper_adv_FK": 0,
		"keeper_adv_CK": 0,
		"keeper_adv_OG": 0,
		"keeper_adv_PSxG": 0.7,
		"keeper_adv_PSxG/SoT": 0.13,
		"keeper_adv_PSxG+/-": "+0.7",
		"keeper_adv_/90": "+0.33",
		"keeper_adv_Cmp": 14,
		"keeper_adv_Att": 25,
		"keeper_adv_Cmp%": 56,
		"keeper_adv_Att__1": 61,
		"keeper_adv_Thr": 11,
		"keeper_adv_Launch%": 31.1,
		"keeper_adv_AvgLen": 31.5,
		"keeper_adv_Att__2": 10,
		"keeper_adv_Launch%__1": 60,
		"keeper_adv_AvgLen__1": 49.4,
		"keeper_adv_Opp": 9,
		"keeper_adv_Stp": 3,
		"keeper_adv_Stp%": 33.3,
		"keeper_adv_#OPA": 1,
		"keeper_adv_#OPA/90": 0.5,
		"keeper_adv_AvgDist": 16,
		"keeper_adv_Matches": "Matches"
	},
	"8": {
		"keeper_Player": "Timo Horn\\Timo-Horn",
		"keeper_Nation": "de GER",
		"keeper_Pos": "GK",
		"keeper_Squad": "Köln",
		"keeper_Age": "27-173",
		"keeper_Born": 1993,
		"keeper_MP": 6,
		"keeper_Starts": 6,
		"keeper_Min": 540,
		"keeper_GA": 11,
		"keeper_GA90": 1.83,
		"keeper_SoTA": 28,
		"keeper_Saves": 21,
		"keeper_Save%": ".750",
		"keeper_W": 0,
		"keeper_D": 2,
		"keeper_L": 4,
		"keeper_CS": 0,
		"keeper_CS%": 0,
		"keeper_PKatt": 4,
		"keeper_PKA": 4,
		"keeper_PKsv": 0,
		"keeper_PKm": 0,
		"keeper_Matches": "Matches",
		"code": "3cd9e95a",
		"url": "/en/players/3cd9e95a/Timo-Horn",
		"keeper_adv_Player": "Timo Horn\\Timo-Horn",
		"keeper_adv_Nation": "de GER",
		"keeper_adv_Pos": "GK",
		"keeper_adv_Squad": "Köln",
		"keeper_adv_Age": "27-173",
		"keeper_adv_Born": 1993,
		"keeper_adv_90s": 6,
		"keeper_adv_GA": 11,
		"keeper_adv_PKA": 4,
		"keeper_adv_FK": 0,
		"keeper_adv_CK": 2,
		"keeper_adv_OG": 0,
		"keeper_adv_PSxG": 8.2,
		"keeper_adv_PSxG/SoT": 0.22,
		"keeper_adv_PSxG+/-": -0.8,
		"keeper_adv_/90": -0.17,
		"keeper_adv_Cmp": 46,
		"keeper_adv_Att": 96,
		"keeper_adv_Cmp%": 47.9,
		"keeper_adv_Att__1": 182,
		"keeper_adv_Thr": 20,
		"keeper_adv_Launch%": 46.7,
		"keeper_adv_AvgLen": 38.1,
		"keeper_adv_Att__2": 28,
		"keeper_adv_Launch%__1": 39.3,
		"keeper_adv_AvgLen__1": 36.8,
		"keeper_adv_Opp": 36,
		"keeper_adv_Stp": 2,
		"keeper_adv_Stp%": 5.6,
		"keeper_adv_#OPA": 6,
		"keeper_adv_#OPA/90": 1.2,
		"keeper_adv_AvgDist": 16.5,
		"keeper_adv_Matches": "Matches"
	},
	"9": {
		"keeper_Player": "Lukáš Hrádecký\\Lukas-Hradecky",
		"keeper_Nation": "fi FIN",
		"keeper_Pos": "GK",
		"keeper_Squad": "Leverkusen",
		"keeper_Age": "30-343",
		"keeper_Born": 1989,
		"keeper_MP": 5,
		"keeper_Starts": 5,
		"keeper_Min": 450,
		"keeper_GA": 3,
		"keeper_GA90": 0.6,
		"keeper_SoTA": 8,
		"keeper_Saves": 5,
		"keeper_Save%": ".625",
		"keeper_W": 2,
		"keeper_D": 3,
		"keeper_L": 0,
		"keeper_CS": 2,
		"keeper_CS%": 40,
		"keeper_PKatt": 0,
		"keeper_PKA": 0,
		"keeper_PKsv": 0,
		"keeper_PKm": 0,
		"keeper_Matches": "Matches",
		"code": "ad3389d5",
		"url": "/en/players/ad3389d5/Lukas-Hradecky",
		"keeper_adv_Player": "Lukáš Hrádecký\\Lukas-Hradecky",
		"keeper_adv_Nation": "fi FIN",
		"keeper_adv_Pos": "GK",
		"keeper_adv_Squad": "Leverkusen",
		"keeper_adv_Age": "30-343",
		"keeper_adv_Born": 1989,
		"keeper_adv_90s": 5,
		"keeper_adv_GA": 3,
		"keeper_adv_PKA": 0,
		"keeper_adv_FK": 0,
		"keeper_adv_CK": 0,
		"keeper_adv_OG": 0,
		"keeper_adv_PSxG": 2.7,
		"keeper_adv_PSxG/SoT": 0.33,
		"keeper_adv_PSxG+/-": -0.3,
		"keeper_adv_/90": -0.07,
		"keeper_adv_Cmp": 37,
		"keeper_adv_Att": 86,
		"keeper_adv_Cmp%": 43,
		"keeper_adv_Att__1": 198,
		"keeper_adv_Thr": 26,
		"keeper_adv_Launch%": 35.9,
		"keeper_adv_AvgLen": 34.5,
		"keeper_adv_Att__2": 33,
		"keeper_adv_Launch%__1": 45.5,
		"keeper_adv_AvgLen__1": 35.4,
		"keeper_adv_Opp": 35,
		"keeper_adv_Stp": 2,
		"keeper_adv_Stp%": 5.7,
		"keeper_adv_#OPA": 8,
		"keeper_adv_#OPA/90": 1.6,
		"keeper_adv_AvgDist": 19.3,
		"keeper_adv_Matches": "Matches"
	},
	"10": {
		"keeper_Player": "Gregor Kobel\\Gregor-Kobel",
		"keeper_Nation": "ch SUI",
		"keeper_Pos": "GK",
		"keeper_Squad": "Stuttgart",
		"keeper_Age": "22-331",
		"keeper_Born": 1997,
		"keeper_MP": 6,
		"keeper_Starts": 6,
		"keeper_Min": 540,
		"keeper_GA": 7,
		"keeper_GA90": 1.17,
		"keeper_SoTA": 23,
		"keeper_Saves": 17,
		"keeper_Save%": ".739",
		"keeper_W": 2,
		"keeper_D": 3,
		"keeper_L": 1,
		"keeper_CS": 1,
		"keeper_CS%": 16.7,
		"keeper_PKatt": 1,
		"keeper_PKA": 1,
		"keeper_PKsv": 0,
		"keeper_PKm": 0,
		"keeper_Matches": "Matches",
		"code": "cd59b9df",
		"url": "/en/players/cd59b9df/Gregor-Kobel",
		"keeper_adv_Player": "Gregor Kobel\\Gregor-Kobel",
		"keeper_adv_Nation": "ch SUI",
		"keeper_adv_Pos": "GK",
		"keeper_adv_Squad": "Stuttgart",
		"keeper_adv_Age": "22-331",
		"keeper_adv_Born": 1997,
		"keeper_adv_90s": 6,
		"keeper_adv_GA": 7,
		"keeper_adv_PKA": 1,
		"keeper_adv_FK": 0,
		"keeper_adv_CK": 1,
		"keeper_adv_OG": 0,
		"keeper_adv_PSxG": 6.1,
		"keeper_adv_PSxG/SoT": 0.23,
		"keeper_adv_PSxG+/-": -0.9,
		"keeper_adv_/90": -0.15,
		"keeper_adv_Cmp": 35,
		"keeper_adv_Att": 70,
		"keeper_adv_Cmp%": 50,
		"keeper_adv_Att__1": 166,
		"keeper_adv_Thr": 31,
		"keeper_adv_Launch%": 34.9,
		"keeper_adv_AvgLen": 32.3,
		"keeper_adv_Att__2": 48,
		"keeper_adv_Launch%__1": 25,
		"keeper_adv_AvgLen__1": 28.3,
		"keeper_adv_Opp": 51,
		"keeper_adv_Stp": 1,
		"keeper_adv_Stp%": 2,
		"keeper_adv_#OPA": 6,
		"keeper_adv_#OPA/90": 1,
		"keeper_adv_AvgDist": 14.4,
		"keeper_adv_Matches": "Matches"
	},
	"11": {
		"keeper_Player": "Andreas Luthe\\Andreas-Luthe",
		"keeper_Nation": "de GER",
		"keeper_Pos": "GK",
		"keeper_Squad": "Union Berlin",
		"keeper_Age": "33-236",
		"keeper_Born": 1987,
		"keeper_MP": 5,
		"keeper_Starts": 5,
		"keeper_Min": 450,
		"keeper_GA": 6,
		"keeper_GA90": 1.2,
		"keeper_SoTA": 19,
		"keeper_Saves": 12,
		"keeper_Save%": ".684",
		"keeper_W": 1,
		"keeper_D": 3,
		"keeper_L": 1,
		"keeper_CS": 1,
		"keeper_CS%": 20,
		"keeper_PKatt": 0,
		"keeper_PKA": 0,
		"keeper_PKsv": 0,
		"keeper_PKm": 0,
		"keeper_Matches": "Matches",
		"code": "7fe12375",
		"url": "/en/players/7fe12375/Andreas-Luthe",
		"keeper_adv_Player": "Andreas Luthe\\Andreas-Luthe",
		"keeper_adv_Nation": "de GER",
		"keeper_adv_Pos": "GK",
		"keeper_adv_Squad": "Union Berlin",
		"keeper_adv_Age": "33-236",
		"keeper_adv_Born": 1987,
		"keeper_adv_90s": 5,
		"keeper_adv_GA": 6,
		"keeper_adv_PKA": 0,
		"keeper_adv_FK": 0,
		"keeper_adv_CK": 2,
		"keeper_adv_OG": 0,
		"keeper_adv_PSxG": 3.6,
		"keeper_adv_PSxG/SoT": 0.19,
		"keeper_adv_PSxG+/-": -2.4,
		"keeper_adv_/90": -0.47,
		"keeper_adv_Cmp": 31,
		"keeper_adv_Att": 92,
		"keeper_adv_Cmp%": 33.7,
		"keeper_adv_Att__1": 153,
		"keeper_adv_Thr": 13,
		"keeper_adv_Launch%": 47.1,
		"keeper_adv_AvgLen": 39.8,
		"keeper_adv_Att__2": 26,
		"keeper_adv_Launch%__1": 76.9,
		"keeper_adv_AvgLen__1": 53.8,
		"keeper_adv_Opp": 37,
		"keeper_adv_Stp": 1,
		"keeper_adv_Stp%": 2.7,
		"keeper_adv_#OPA": 0,
		"keeper_adv_#OPA/90": 0,
		"keeper_adv_AvgDist": 13.7,
		"keeper_adv_Matches": "Matches"
	},
	"12": {
		"keeper_Player": "Florian Müller\\Florian-Muller",
		"keeper_Nation": "de GER",
		"keeper_Pos": "GK",
		"keeper_Squad": "Freiburg",
		"keeper_Age": "22-354",
		"keeper_Born": 1997,
		"keeper_MP": 5,
		"keeper_Starts": 5,
		"keeper_Min": 450,
		"keeper_GA": 9,
		"keeper_GA90": 1.8,
		"keeper_SoTA": 24,
		"keeper_Saves": 16,
		"keeper_Save%": ".667",
		"keeper_W": 1,
		"keeper_D": 3,
		"keeper_L": 1,
		"keeper_CS": 0,
		"keeper_CS%": 0,
		"keeper_PKatt": 1,
		"keeper_PKA": 1,
		"keeper_PKsv": 0,
		"keeper_PKm": 0,
		"keeper_Matches": "Matches",
		"code": "cbac6ec9",
		"url": "/en/players/cbac6ec9/Florian-Muller",
		"keeper_adv_Player": "Florian Müller\\Florian-Muller",
		"keeper_adv_Nation": "de GER",
		"keeper_adv_Pos": "GK",
		"keeper_adv_Squad": "Freiburg",
		"keeper_adv_Age": "22-354",
		"keeper_adv_Born": 1997,
		"keeper_adv_90s": 5,
		"keeper_adv_GA": 9,
		"keeper_adv_PKA": 1,
		"keeper_adv_FK": 1,
		"keeper_adv_CK": 1,
		"keeper_adv_OG": 0,
		"keeper_adv_PSxG": 8.5,
		"keeper_adv_PSxG/SoT": 0.32,
		"keeper_adv_PSxG+/-": -0.5,
		"keeper_adv_/90": -0.09,
		"keeper_adv_Cmp": 31,
		"keeper_adv_Att": 88,
		"keeper_adv_Cmp%": 35.2,
		"keeper_adv_Att__1": 132,
		"keeper_adv_Thr": 12,
		"keeper_adv_Launch%": 36.4,
		"keeper_adv_AvgLen": 36.3,
		"keeper_adv_Att__2": 53,
		"keeper_adv_Launch%__1": 75.5,
		"keeper_adv_AvgLen__1": 58.9,
		"keeper_adv_Opp": 39,
		"keeper_adv_Stp": 2,
		"keeper_adv_Stp%": 5.1,
		"keeper_adv_#OPA": 1,
		"keeper_adv_#OPA/90": 0.2,
		"keeper_adv_AvgDist": 11.8,
		"keeper_adv_Matches": "Matches"
	},
	"13": {
		"keeper_Player": "Manuel Neuer\\Manuel-Neuer",
		"keeper_Nation": "de GER",
		"keeper_Pos": "GK",
		"keeper_Squad": "Bayern Munich",
		"keeper_Age": "34-219",
		"keeper_Born": 1986,
		"keeper_MP": 6,
		"keeper_Starts": 6,
		"keeper_Min": 540,
		"keeper_GA": 9,
		"keeper_GA90": 1.5,
		"keeper_SoTA": 22,
		"keeper_Saves": 13,
		"keeper_Save%": ".636",
		"keeper_W": 5,
		"keeper_D": 0,
		"keeper_L": 1,
		"keeper_CS": 2,
		"keeper_CS%": 33.3,
		"keeper_PKatt": 1,
		"keeper_PKA": 1,
		"keeper_PKsv": 0,
		"keeper_PKm": 0,
		"keeper_Matches": "Matches",
		"code": "8778c910",
		"url": "/en/players/8778c910/Manuel-Neuer",
		"keeper_adv_Player": "Manuel Neuer\\Manuel-Neuer",
		"keeper_adv_Nation": "de GER",
		"keeper_adv_Pos": "GK",
		"keeper_adv_Squad": "Bayern Munich",
		"keeper_adv_Age": "34-219",
		"keeper_adv_Born": 1986,
		"keeper_adv_90s": 6,
		"keeper_adv_GA": 9,
		"keeper_adv_PKA": 1,
		"keeper_adv_FK": 0,
		"keeper_adv_CK": 1,
		"keeper_adv_OG": 0,
		"keeper_adv_PSxG": 9.5,
		"keeper_adv_PSxG/SoT": 0.43,
		"keeper_adv_PSxG+/-": "+1.5",
		"keeper_adv_/90": "+0.30",
		"keeper_adv_Cmp": 29,
		"keeper_adv_Att": 42,
		"keeper_adv_Cmp%": 69,
		"keeper_adv_Att__1": 172,
		"keeper_adv_Thr": 33,
		"keeper_adv_Launch%": 22.7,
		"keeper_adv_AvgLen": 29,
		"keeper_adv_Att__2": 23,
		"keeper_adv_Launch%__1": 13,
		"keeper_adv_AvgLen__1": 27.6,
		"keeper_adv_Opp": 32,
		"keeper_adv_Stp": 0,
		"keeper_adv_Stp%": 0,
		"keeper_adv_#OPA": 0,
		"keeper_adv_#OPA/90": 0,
		"keeper_adv_AvgDist": 13.3,
		"keeper_adv_Matches": "Matches"
	},
	"14": {
		"keeper_Player": "Stefan Ortega\\Stefan-Ortega",
		"keeper_Nation": "de GER",
		"keeper_Pos": "GK",
		"keeper_Squad": "Arminia",
		"keeper_Age": "27-361",
		"keeper_Born": 1992,
		"keeper_MP": 6,
		"keeper_Starts": 6,
		"keeper_Min": 540,
		"keeper_GA": 10,
		"keeper_GA90": 1.67,
		"keeper_SoTA": 34,
		"keeper_Saves": 24,
		"keeper_Save%": ".706",
		"keeper_W": 1,
		"keeper_D": 1,
		"keeper_L": 4,
		"keeper_CS": 1,
		"keeper_CS%": 16.7,
		"keeper_PKatt": 0,
		"keeper_PKA": 0,
		"keeper_PKsv": 0,
		"keeper_PKm": 0,
		"keeper_Matches": "Matches",
		"code": "c1242d4e",
		"url": "/en/players/c1242d4e/Stefan-Ortega",
		"keeper_adv_Player": "Stefan Ortega\\Stefan-Ortega",
		"keeper_adv_Nation": "de GER",
		"keeper_adv_Pos": "GK",
		"keeper_adv_Squad": "Arminia",
		"keeper_adv_Age": "27-361",
		"keeper_adv_Born": 1992,
		"keeper_adv_90s": 6,
		"keeper_adv_GA": 10,
		"keeper_adv_PKA": 0,
		"keeper_adv_FK": 0,
		"keeper_adv_CK": 1,
		"keeper_adv_OG": 0,
		"keeper_adv_PSxG": 8.1,
		"keeper_adv_PSxG/SoT": 0.34,
		"keeper_adv_PSxG+/-": "+0.1",
		"keeper_adv_/90": "+0.02",
		"keeper_adv_Cmp": 67,
		"keeper_adv_Att": 136,
		"keeper_adv_Cmp%": 49.3,
		"keeper_adv_Att__1": 272,
		"keeper_adv_Thr": 19,
		"keeper_adv_Launch%": 45.2,
		"keeper_adv_AvgLen": 39.8,
		"keeper_adv_Att__2": 34,
		"keeper_adv_Launch%__1": 38.2,
		"keeper_adv_AvgLen__1": 39.9,
		"keeper_adv_Opp": 57,
		"keeper_adv_Stp": 4,
		"keeper_adv_Stp%": 7,
		"keeper_adv_#OPA": 6,
		"keeper_adv_#OPA/90": 1.2,
		"keeper_adv_AvgDist": 14.4,
		"keeper_adv_Matches": "Matches"
	},
	"15": {
		"keeper_Player": "Jiří Pavlenka\\Jiri-Pavlenka",
		"keeper_Nation": "cz CZE",
		"keeper_Pos": "GK",
		"keeper_Squad": "Werder Bremen",
		"keeper_Age": "28-201",
		"keeper_Born": 1992,
		"keeper_MP": 6,
		"keeper_Starts": 6,
		"keeper_Min": 540,
		"keeper_GA": 8,
		"keeper_GA90": 1.33,
		"keeper_SoTA": 28,
		"keeper_Saves": 20,
		"keeper_Save%": ".714",
		"keeper_W": 2,
		"keeper_D": 3,
		"keeper_L": 1,
		"keeper_CS": 1,
		"keeper_CS%": 16.7,
		"keeper_PKatt": 0,
		"keeper_PKA": 0,
		"keeper_PKsv": 0,
		"keeper_PKm": 0,
		"keeper_Matches": "Matches",
		"code": "0a1cb833",
		"url": "/en/players/0a1cb833/Jiri-Pavlenka",
		"keeper_adv_Player": "Jiří Pavlenka\\Jiri-Pavlenka",
		"keeper_adv_Nation": "cz CZE",
		"keeper_adv_Pos": "GK",
		"keeper_adv_Squad": "Werder Bremen",
		"keeper_adv_Age": "28-201",
		"keeper_adv_Born": 1992,
		"keeper_adv_90s": 6,
		"keeper_adv_GA": 8,
		"keeper_adv_PKA": 0,
		"keeper_adv_FK": 0,
		"keeper_adv_CK": 1,
		"keeper_adv_OG": 0,
		"keeper_adv_PSxG": 5.1,
		"keeper_adv_PSxG/SoT": 0.23,
		"keeper_adv_PSxG+/-": -1.9,
		"keeper_adv_/90": -0.38,
		"keeper_adv_Cmp": 38,
		"keeper_adv_Att": 84,
		"keeper_adv_Cmp%": 45.2,
		"keeper_adv_Att__1": 113,
		"keeper_adv_Thr": 26,
		"keeper_adv_Launch%": 49.6,
		"keeper_adv_AvgLen": 42.4,
		"keeper_adv_Att__2": 38,
		"keeper_adv_Launch%__1": 73.7,
		"keeper_adv_AvgLen__1": 54.1,
		"keeper_adv_Opp": 54,
		"keeper_adv_Stp": 2,
		"keeper_adv_Stp%": 3.7,
		"keeper_adv_#OPA": 3,
		"keeper_adv_#OPA/90": 0.6,
		"keeper_adv_AvgDist": 12.8,
		"keeper_adv_Matches": "Matches"
	},
	"16": {
		"keeper_Player": "Philipp Pentke\\Philipp-Pentke",
		"keeper_Nation": "de GER",
		"keeper_Pos": "GK",
		"keeper_Squad": "Hoffenheim",
		"keeper_Age": "35-184",
		"keeper_Born": 1985,
		"keeper_MP": 1,
		"keeper_Starts": 1,
		"keeper_Min": 90,
		"keeper_GA": 1,
		"keeper_GA90": 1,
		"keeper_SoTA": 2,
		"keeper_Saves": 1,
		"keeper_Save%": ".500",
		"keeper_W": 0,
		"keeper_D": 1,
		"keeper_L": 0,
		"keeper_CS": 0,
		"keeper_CS%": 0,
		"keeper_PKatt": 0,
		"keeper_PKA": 0,
		"keeper_PKsv": 0,
		"keeper_PKm": 0,
		"keeper_Matches": "Matches",
		"code": "c41f7379",
		"url": "/en/players/c41f7379/Philipp-Pentke",
		"keeper_adv_Player": "Philipp Pentke\\Philipp-Pentke",
		"keeper_adv_Nation": "de GER",
		"keeper_adv_Pos": "GK",
		"keeper_adv_Squad": "Hoffenheim",
		"keeper_adv_Age": "35-184",
		"keeper_adv_Born": 1985,
		"keeper_adv_90s": 1,
		"keeper_adv_GA": 1,
		"keeper_adv_PKA": 0,
		"keeper_adv_FK": 0,
		"keeper_adv_CK": 0,
		"keeper_adv_OG": 0,
		"keeper_adv_PSxG": 0.4,
		"keeper_adv_PSxG/SoT": 0.21,
		"keeper_adv_PSxG+/-": -0.6,
		"keeper_adv_/90": -0.57,
		"keeper_adv_Cmp": 2,
		"keeper_adv_Att": 6,
		"keeper_adv_Cmp%": 33.3,
		"keeper_adv_Att__1": 25,
		"keeper_adv_Thr": 5,
		"keeper_adv_Launch%": 20,
		"keeper_adv_AvgLen": 29.8,
		"keeper_adv_Att__2": 4,
		"keeper_adv_Launch%__1": 25,
		"keeper_adv_AvgLen__1": 31.5,
		"keeper_adv_Opp": 2,
		"keeper_adv_Stp": 0,
		"keeper_adv_Stp%": 0,
		"keeper_adv_#OPA": 1,
		"keeper_adv_#OPA/90": 1,
		"keeper_adv_AvgDist": 20.3,
		"keeper_adv_Matches": "Matches"
	},
	"17": {
		"keeper_Player": "Pavao Pervan\\Pavao-Pervan",
		"keeper_Nation": "at AUT",
		"keeper_Pos": "GK",
		"keeper_Squad": "Wolfsburg",
		"keeper_Age": "32-354",
		"keeper_Born": 1987,
		"keeper_MP": 1,
		"keeper_Starts": 1,
		"keeper_Min": 90,
		"keeper_GA": 1,
		"keeper_GA90": 1,
		"keeper_SoTA": 7,
		"keeper_Saves": 5,
		"keeper_Save%": ".857",
		"keeper_W": 0,
		"keeper_D": 1,
		"keeper_L": 0,
		"keeper_CS": 0,
		"keeper_CS%": 0,
		"keeper_PKatt": 0,
		"keeper_PKA": 0,
		"keeper_PKsv": 0,
		"keeper_PKm": 0,
		"keeper_Matches": "Matches",
		"code": "c89e8aae",
		"url": "/en/players/c89e8aae/Pavao-Pervan",
		"keeper_adv_Player": "Pavao Pervan\\Pavao-Pervan",
		"keeper_adv_Nation": "at AUT",
		"keeper_adv_Pos": "GK",
		"keeper_adv_Squad": "Wolfsburg",
		"keeper_adv_Age": "32-354",
		"keeper_adv_Born": 1987,
		"keeper_adv_90s": 1,
		"keeper_adv_GA": 1,
		"keeper_adv_PKA": 0,
		"keeper_adv_FK": 0,
		"keeper_adv_CK": 1,
		"keeper_adv_OG": 0,
		"keeper_adv_PSxG": 2.7,
		"keeper_adv_PSxG/SoT": 0.39,
		"keeper_adv_PSxG+/-": "+1.7",
		"keeper_adv_/90": "+1.72",
		"keeper_adv_Cmp": 8,
		"keeper_adv_Att": 19,
		"keeper_adv_Cmp%": 42.1,
		"keeper_adv_Att__1": 23,
		"keeper_adv_Thr": 1,
		"keeper_adv_Launch%": 56.5,
		"keeper_adv_AvgLen": 43.2,
		"keeper_adv_Att__2": 9,
		"keeper_adv_Launch%__1": 66.7,
		"keeper_adv_AvgLen__1": 53.4,
		"keeper_adv_Opp": 13,
		"keeper_adv_Stp": 1,
		"keeper_adv_Stp%": 7.7,
		"keeper_adv_#OPA": 0,
		"keeper_adv_#OPA/90": 0,
		"keeper_adv_AvgDist": 11.3,
		"keeper_adv_Matches": "Matches"
	},
	"18": {
		"keeper_Player": "Frederik Rønnow\\Frederik-Ronnow",
		"keeper_Nation": "dk DEN",
		"keeper_Pos": "GK",
		"keeper_Squad": "Schalke 04",
		"keeper_Age": "28-089",
		"keeper_Born": 1992,
		"keeper_MP": 4,
		"keeper_Starts": 3,
		"keeper_Min": 315,
		"keeper_GA": 6,
		"keeper_GA90": 1.71,
		"keeper_SoTA": 24,
		"keeper_Saves": 20,
		"keeper_Save%": ".833",
		"keeper_W": 0,
		"keeper_D": 2,
		"keeper_L": 1,
		"keeper_CS": 0,
		"keeper_CS%": 0,
		"keeper_PKatt": 2,
		"keeper_PKA": 2,
		"keeper_PKsv": 0,
		"keeper_PKm": 0,
		"keeper_Matches": "Matches",
		"code": "a70b8345",
		"url": "/en/players/a70b8345/Frederik-Ronnow",
		"keeper_adv_Player": "Frederik Rønnow\\Frederik-Ronnow",
		"keeper_adv_Nation": "dk DEN",
		"keeper_adv_Pos": "GK",
		"keeper_adv_Squad": "Schalke 04",
		"keeper_adv_Age": "28-089",
		"keeper_adv_Born": 1992,
		"keeper_adv_90s": 3.5,
		"keeper_adv_GA": 6,
		"keeper_adv_PKA": 2,
		"keeper_adv_FK": 0,
		"keeper_adv_CK": 3,
		"keeper_adv_OG": 0,
		"keeper_adv_PSxG": 7.2,
		"keeper_adv_PSxG/SoT": 0.23,
		"keeper_adv_PSxG+/-": "+1.2",
		"keeper_adv_/90": "+0.33",
		"keeper_adv_Cmp": 19,
		"keeper_adv_Att": 44,
		"keeper_adv_Cmp%": 43.2,
		"keeper_adv_Att__1": 92,
		"keeper_adv_Thr": 23,
		"keeper_adv_Launch%": 32.6,
		"keeper_adv_AvgLen": 33.3,
		"keeper_adv_Att__2": 31,
		"keeper_adv_Launch%__1": 45.2,
		"keeper_adv_AvgLen__1": 40.5,
		"keeper_adv_Opp": 24,
		"keeper_adv_Stp": 0,
		"keeper_adv_Stp%": 0,
		"keeper_adv_#OPA": 0,
		"keeper_adv_#OPA/90": 0,
		"keeper_adv_AvgDist": 13.2,
		"keeper_adv_Matches": "Matches"
	},
	"19": {
		"keeper_Player": "Alexander Schwolow\\Alexander-Schwolow",
		"keeper_Nation": "de GER",
		"keeper_Pos": "GK",
		"keeper_Squad": "Hertha BSC",
		"keeper_Age": "28-152",
		"keeper_Born": 1992,
		"keeper_MP": 5,
		"keeper_Starts": 5,
		"keeper_Min": 450,
		"keeper_GA": 12,
		"keeper_GA90": 2.4,
		"keeper_SoTA": 25,
		"keeper_Saves": 16,
		"keeper_Save%": ".640",
		"keeper_W": 1,
		"keeper_D": 0,
		"keeper_L": 4,
		"keeper_CS": 0,
		"keeper_CS%": 0,
		"keeper_PKatt": 3,
		"keeper_PKA": 3,
		"keeper_PKsv": 0,
		"keeper_PKm": 0,
		"keeper_Matches": "Matches",
		"code": "0d55d942",
		"url": "/en/players/0d55d942/Alexander-Schwolow",
		"keeper_adv_Player": "Alexander Schwolow\\Alexander-Schwolow",
		"keeper_adv_Nation": "de GER",
		"keeper_adv_Pos": "GK",
		"keeper_adv_Squad": "Hertha BSC",
		"keeper_adv_Age": "28-152",
		"keeper_adv_Born": 1992,
		"keeper_adv_90s": 5,
		"keeper_adv_GA": 12,
		"keeper_adv_PKA": 3,
		"keeper_adv_FK": 0,
		"keeper_adv_CK": 0,
		"keeper_adv_OG": 0,
		"keeper_adv_PSxG": 10.4,
		"keeper_adv_PSxG/SoT": 0.33,
		"keeper_adv_PSxG+/-": -1.6,
		"keeper_adv_/90": -0.33,
		"keeper_adv_Cmp": 43,
		"keeper_adv_Att": 93,
		"keeper_adv_Cmp%": 46.2,
		"keeper_adv_Att__1": 148,
		"keeper_adv_Thr": 24,
		"keeper_adv_Launch%": 38.5,
		"keeper_adv_AvgLen": 35.7,
		"keeper_adv_Att__2": 58,
		"keeper_adv_Launch%__1": 62.1,
		"keeper_adv_AvgLen__1": 49.5,
		"keeper_adv_Opp": 53,
		"keeper_adv_Stp": 5,
		"keeper_adv_Stp%": 9.4,
		"keeper_adv_#OPA": 3,
		"keeper_adv_#OPA/90": 0.6,
		"keeper_adv_AvgDist": 15.5,
		"keeper_adv_Matches": "Matches"
	},
	"20": {
		"keeper_Player": "Yann Sommer\\Yann-Sommer",
		"keeper_Nation": "ch SUI",
		"keeper_Pos": "GK",
		"keeper_Squad": "M'Gladbach",
		"keeper_Age": "31-320",
		"keeper_Born": 1988,
		"keeper_MP": 6,
		"keeper_Starts": 6,
		"keeper_Min": 540,
		"keeper_GA": 8,
		"keeper_GA90": 1.33,
		"keeper_SoTA": 21,
		"keeper_Saves": 14,
		"keeper_Save%": ".667",
		"keeper_W": 3,
		"keeper_D": 2,
		"keeper_L": 1,
		"keeper_CS": 1,
		"keeper_CS%": 16.7,
		"keeper_PKatt": 1,
		"keeper_PKA": 1,
		"keeper_PKsv": 0,
		"keeper_PKm": 0,
		"keeper_Matches": "Matches",
		"code": "420c18a1",
		"url": "/en/players/420c18a1/Yann-Sommer",
		"keeper_adv_Player": "Yann Sommer\\Yann-Sommer",
		"keeper_adv_Nation": "ch SUI",
		"keeper_adv_Pos": "GK",
		"keeper_adv_Squad": "M'Gladbach",
		"keeper_adv_Age": "31-320",
		"keeper_adv_Born": 1988,
		"keeper_adv_90s": 6,
		"keeper_adv_GA": 8,
		"keeper_adv_PKA": 1,
		"keeper_adv_FK": 0,
		"keeper_adv_CK": 1,
		"keeper_adv_OG": 0,
		"keeper_adv_PSxG": 6.3,
		"keeper_adv_PSxG/SoT": 0.3,
		"keeper_adv_PSxG+/-": -1.7,
		"keeper_adv_/90": -0.35,
		"keeper_adv_Cmp": 20,
		"keeper_adv_Att": 48,
		"keeper_adv_Cmp%": 41.7,
		"keeper_adv_Att__1": 167,
		"keeper_adv_Thr": 22,
		"keeper_adv_Launch%": 26.9,
		"keeper_adv_AvgLen": 31.2,
		"keeper_adv_Att__2": 29,
		"keeper_adv_Launch%__1": 10.3,
		"keeper_adv_AvgLen__1": 19.2,
		"keeper_adv_Opp": 37,
		"keeper_adv_Stp": 3,
		"keeper_adv_Stp%": 8.1,
		"keeper_adv_#OPA": 3,
		"keeper_adv_#OPA/90": 0.6,
		"keeper_adv_AvgDist": 15.7,
		"keeper_adv_Matches": "Matches"
	},
	"21": {
		"keeper_Player": "Kevin Trapp\\Kevin-Trapp",
		"keeper_Nation": "de GER",
		"keeper_Pos": "GK",
		"keeper_Squad": "Eint Frankfurt",
		"keeper_Age": "30-116",
		"keeper_Born": 1990,
		"keeper_MP": 6,
		"keeper_Starts": 6,
		"keeper_Min": 540,
		"keeper_GA": 10,
		"keeper_GA90": 1.67,
		"keeper_SoTA": 31,
		"keeper_Saves": 22,
		"keeper_Save%": ".677",
		"keeper_W": 2,
		"keeper_D": 3,
		"keeper_L": 1,
		"keeper_CS": 0,
		"keeper_CS%": 0,
		"keeper_PKatt": 0,
		"keeper_PKA": 0,
		"keeper_PKsv": 0,
		"keeper_PKm": 0,
		"keeper_Matches": "Matches",
		"code": "ce17b5eb",
		"url": "/en/players/ce17b5eb/Kevin-Trapp",
		"keeper_adv_Player": "Kevin Trapp\\Kevin-Trapp",
		"keeper_adv_Nation": "de GER",
		"keeper_adv_Pos": "GK",
		"keeper_adv_Squad": "Eint Frankfurt",
		"keeper_adv_Age": "30-116",
		"keeper_adv_Born": 1990,
		"keeper_adv_90s": 6,
		"keeper_adv_GA": 10,
		"keeper_adv_PKA": 0,
		"keeper_adv_FK": 0,
		"keeper_adv_CK": 1,
		"keeper_adv_OG": 1,
		"keeper_adv_PSxG": 8.6,
		"keeper_adv_PSxG/SoT": 0.32,
		"keeper_adv_PSxG+/-": "+0.6",
		"keeper_adv_/90": "+0.13",
		"keeper_adv_Cmp": 57,
		"keeper_adv_Att": 106,
		"keeper_adv_Cmp%": 53.8,
		"keeper_adv_Att__1": 178,
		"keeper_adv_Thr": 25,
		"keeper_adv_Launch%": 48.9,
		"keeper_adv_AvgLen": 38.7,
		"keeper_adv_Att__2": 33,
		"keeper_adv_Launch%__1": 57.6,
		"keeper_adv_AvgLen__1": 47.2,
		"keeper_adv_Opp": 48,
		"keeper_adv_Stp": 6,
		"keeper_adv_Stp%": 12.5,
		"keeper_adv_#OPA": 3,
		"keeper_adv_#OPA/90": 0.6,
		"keeper_adv_AvgDist": 15.7,
		"keeper_adv_Matches": "Matches"
	},
	"22": {
		"keeper_Player": "Robin Zentner\\Robin-Zentner",
		"keeper_Nation": "de GER",
		"keeper_Pos": "GK",
		"keeper_Squad": "Mainz 05",
		"keeper_Age": "26-004",
		"keeper_Born": 1994,
		"keeper_MP": 6,
		"keeper_Starts": 6,
		"keeper_Min": 540,
		"keeper_GA": 18,
		"keeper_GA90": 3,
		"keeper_SoTA": 40,
		"keeper_Saves": 24,
		"keeper_Save%": ".600",
		"keeper_W": 0,
		"keeper_D": 0,
		"keeper_L": 6,
		"keeper_CS": 0,
		"keeper_CS%": 0,
		"keeper_PKatt": 2,
		"keeper_PKA": 2,
		"keeper_PKsv": 0,
		"keeper_PKm": 0,
		"keeper_Matches": "Matches",
		"code": "5c4bf6ba",
		"url": "/en/players/5c4bf6ba/Robin-Zentner",
		"keeper_adv_Player": "Robin Zentner\\Robin-Zentner",
		"keeper_adv_Nation": "de GER",
		"keeper_adv_Pos": "GK",
		"keeper_adv_Squad": "Mainz 05",
		"keeper_adv_Age": "26-004",
		"keeper_adv_Born": 1994,
		"keeper_adv_90s": 6,
		"keeper_adv_GA": 18,
		"keeper_adv_PKA": 2,
		"keeper_adv_FK": 0,
		"keeper_adv_CK": 3,
		"keeper_adv_OG": 0,
		"keeper_adv_PSxG": 9.9,
		"keeper_adv_PSxG/SoT": 0.26,
		"keeper_adv_PSxG+/-": -5.1,
		"keeper_adv_/90": -1.02,
		"keeper_adv_Cmp": 28,
		"keeper_adv_Att": 76,
		"keeper_adv_Cmp%": 36.8,
		"keeper_adv_Att__1": 158,
		"keeper_adv_Thr": 31,
		"keeper_adv_Launch%": 36.7,
		"keeper_adv_AvgLen": 35.1,
		"keeper_adv_Att__2": 39,
		"keeper_adv_Launch%__1": 46.2,
		"keeper_adv_AvgLen__1": 42.2,
		"keeper_adv_Opp": 41,
		"keeper_adv_Stp": 2,
		"keeper_adv_Stp%": 4.9,
		"keeper_adv_#OPA": 6,
		"keeper_adv_#OPA/90": 1.2,
		"keeper_adv_AvgDist": 16.3,
		"keeper_adv_Matches": "Matches"
	}
}