{
	"1": {
		"keeper_Player": "Julen Agirrezabala\\a2c1a8d3",
		"keeper_Nation": "es ESP",
		"keeper_Pos": "GK",
		"keeper_Squad": "Athletic Club",
		"keeper_Age": 20,
		"keeper_Born": 2000,
		"keeper_MP": 4,
		"keeper_Starts": 4,
		"keeper_Min": 360,
		"keeper_90s": 4,
		"keeper_GA": 5,
		"keeper_GA90": 1.25,
		"keeper_SoTA": 20,
		"keeper_Saves": 15,
		"keeper_Save%": 75,
		"keeper_W": 1,
		"keeper_D": 2,
		"keeper_L": 1,
		"keeper_CS": 1,
		"keeper_CS%": 25,
		"keeper_PKatt": 0,
		"keeper_PKA": 0,
		"keeper_PKsv": 0,
		"keeper_PKm": 0,
		"keeper_Save%__1": "",
		"keeper_Matches": "Matches",
		"code": "a2c1a8d3",
		"url": "/en/players/a2c1a8d3/Julen-Agirrezabala",
		"keeper_adv_Player": "Julen Agirrezabala\\a2c1a8d3",
		"keeper_adv_Nation": "es ESP",
		"keeper_adv_Pos": "GK",
		"keeper_adv_Squad": "Athletic Club",
		"keeper_adv_Age": 20,
		"keeper_adv_Born": 2000,
		"keeper_adv_90s": 4,
		"keeper_adv_GA": 5,
		"keeper_adv_PKA": 0,
		"keeper_adv_FK": 0,
		"keeper_adv_CK": 0,
		"keeper_adv_OG": 0,
		"keeper_adv_PSxG": 4.6,
		"keeper_adv_PSxG/SoT": 0.25,
		"keeper_adv_PSxG+/-": -0.4,
		"keeper_adv_/90": -0.1,
		"keeper_adv_Cmp": 10,
		"keeper_adv_Att": 31,
		"keeper_adv_Cmp%": 32.3,
		"keeper_adv_Att__1": 56,
		"keeper_adv_Thr": 10,
		"keeper_adv_Launch%": 37.5,
		"keeper_adv_AvgLen": 36.8,
		"keeper_adv_Att__2": 26,
		"keeper_adv_Launch%__1": 38.5,
		"keeper_adv_AvgLen__1": 38.3,
		"keeper_adv_Opp": 35,
		"keeper_adv_Stp": 2,
		"keeper_adv_Stp%": 5.7,
		"keeper_adv_#OPA": 5,
		"keeper_adv_#OPA/90": 1.25,
		"keeper_adv_AvgDist": 17.3,
		"keeper_adv_Matches": "Matches"
	},
	"2": {
		"keeper_Player": "Sergio Asenjo\\9f0ea33f",
		"keeper_Nation": "es ESP",
		"keeper_Pos": "GK",
		"keeper_Squad": "Villarreal",
		"keeper_Age": 32,
		"keeper_Born": 1989,
		"keeper_MP": 6,
		"keeper_Starts": 6,
		"keeper_Min": 540,
		"keeper_90s": 6,
		"keeper_GA": 9,
		"keeper_GA90": 1.5,
		"keeper_SoTA": 27,
		"keeper_Saves": 19,
		"keeper_Save%": 70.4,
		"keeper_W": 2,
		"keeper_D": 2,
		"keeper_L": 2,
		"keeper_CS": 0,
		"keeper_CS%": 0,
		"keeper_PKatt": 1,
		"keeper_PKA": 1,
		"keeper_PKsv": 0,
		"keeper_PKm": 0,
		"keeper_Save%__1": 0,
		"keeper_Matches": "Matches",
		"code": "9f0ea33f",
		"url": "/en/players/9f0ea33f/Sergio-Asenjo",
		"keeper_adv_Player": "Sergio Asenjo\\9f0ea33f",
		"keeper_adv_Nation": "es ESP",
		"keeper_adv_Pos": "GK",
		"keeper_adv_Squad": "Villarreal",
		"keeper_adv_Age": 32,
		"keeper_adv_Born": 1989,
		"keeper_adv_90s": 6,
		"keeper_adv_GA": 9,
		"keeper_adv_PKA": 1,
		"keeper_adv_FK": 0,
		"keeper_adv_CK": 1,
		"keeper_adv_OG": 0,
		"keeper_adv_PSxG": 9.1,
		"keeper_adv_PSxG/SoT": 0.31,
		"keeper_adv_PSxG+/-": "+0.1",
		"keeper_adv_/90": "+0.02",
		"keeper_adv_Cmp": 28,
		"keeper_adv_Att": 64,
		"keeper_adv_Cmp%": 43.8,
		"keeper_adv_Att__1": 166,
		"keeper_adv_Thr": 39,
		"keeper_adv_Launch%": 27.1,
		"keeper_adv_AvgLen": 32,
		"keeper_adv_Att__2": 56,
		"keeper_adv_Launch%__1": 33.9,
		"keeper_adv_AvgLen__1": 36.4,
		"keeper_adv_Opp": 73,
		"keeper_adv_Stp": 5,
		"keeper_adv_Stp%": 6.8,
		"keeper_adv_#OPA": 8,
		"keeper_adv_#OPA/90": 1.33,
		"keeper_adv_AvgDist": 14.8,
		"keeper_adv_Matches": "Matches"
	},
	"3": {
		"keeper_Player": "Édgar Badía\\e4346678",
		"keeper_Nation": "es ESP",
		"keeper_Pos": "GK",
		"keeper_Squad": "Elche",
		"keeper_Age": 29,
		"keeper_Born": 1992,
		"keeper_MP": 24,
		"keeper_Starts": 24,
		"keeper_Min": 2160,
		"keeper_90s": 24,
		"keeper_GA": 35,
		"keeper_GA90": 1.46,
		"keeper_SoTA": 106,
		"keeper_Saves": 77,
		"keeper_Save%": 73.6,
		"keeper_W": 8,
		"keeper_D": 5,
		"keeper_L": 11,
		"keeper_CS": 5,
		"keeper_CS%": 20.8,
		"keeper_PKatt": 9,
		"keeper_PKA": 7,
		"keeper_PKsv": 1,
		"keeper_PKm": 1,
		"keeper_Save%__1": 12.5,
		"keeper_Matches": "Matches",
		"code": "e4346678",
		"url": "/en/players/e4346678/Edgar-Badia",
		"keeper_adv_Player": "Édgar Badía\\e4346678",
		"keeper_adv_Nation": "es ESP",
		"keeper_adv_Pos": "GK",
		"keeper_adv_Squad": "Elche",
		"keeper_adv_Age": 29,
		"keeper_adv_Born": 1992,
		"keeper_adv_90s": 24,
		"keeper_adv_GA": 35,
		"keeper_adv_PKA": 7,
		"keeper_adv_FK": 0,
		"keeper_adv_CK": 6,
		"keeper_adv_OG": 0,
		"keeper_adv_PSxG": 40.4,
		"keeper_adv_PSxG/SoT": 0.31,
		"keeper_adv_PSxG+/-": "+5.4",
		"keeper_adv_/90": "+0.22",
		"keeper_adv_Cmp": 211,
		"keeper_adv_Att": 467,
		"keeper_adv_Cmp%": 45.2,
		"keeper_adv_Att__1": 618,
		"keeper_adv_Thr": 100,
		"keeper_adv_Launch%": 50.5,
		"keeper_adv_AvgLen": 39.7,
		"keeper_adv_Att__2": 211,
		"keeper_adv_Launch%__1": 73.5,
		"keeper_adv_AvgLen__1": 51.7,
		"keeper_adv_Opp": 275,
		"keeper_adv_Stp": 24,
		"keeper_adv_Stp%": 8.7,
		"keeper_adv_#OPA": 23,
		"keeper_adv_#OPA/90": 0.96,
		"keeper_adv_AvgDist": 15.8,
		"keeper_adv_Matches": "Matches"
	},
	"4": {
		"keeper_Player": "Yassine Bounou\\f6798fc3",
		"keeper_Nation": "ma MAR",
		"keeper_Pos": "GK",
		"keeper_Squad": "Sevilla",
		"keeper_Age": 30,
		"keeper_Born": 1991,
		"keeper_MP": 31,
		"keeper_Starts": 31,
		"keeper_Min": 2790,
		"keeper_90s": 31,
		"keeper_GA": 24,
		"keeper_GA90": 0.77,
		"keeper_SoTA": 98,
		"keeper_Saves": 75,
		"keeper_Save%": 77.6,
		"keeper_W": 14,
		"keeper_D": 13,
		"keeper_L": 4,
		"keeper_CS": 13,
		"keeper_CS%": 41.9,
		"keeper_PKatt": 4,
		"keeper_PKA": 2,
		"keeper_PKsv": 1,
		"keeper_PKm": 1,
		"keeper_Save%__1": 33.3,
		"keeper_Matches": "Matches",
		"code": "f6798fc3",
		"url": "/en/players/f6798fc3/Yassine-Bounou",
		"keeper_adv_Player": "Yassine Bounou\\f6798fc3",
		"keeper_adv_Nation": "ma MAR",
		"keeper_adv_Pos": "GK",
		"keeper_adv_Squad": "Sevilla",
		"keeper_adv_Age": 30,
		"keeper_adv_Born": 1991,
		"keeper_adv_90s": 31,
		"keeper_adv_GA": 24,
		"keeper_adv_PKA": 2,
		"keeper_adv_FK": 2,
		"keeper_adv_CK": 6,
		"keeper_adv_OG": 0,
		"keeper_adv_PSxG": 28.8,
		"keeper_adv_PSxG/SoT": 0.27,
		"keeper_adv_PSxG+/-": "+4.8",
		"keeper_adv_/90": "+0.15",
		"keeper_adv_Cmp": 187,
		"keeper_adv_Att": 429,
		"keeper_adv_Cmp%": 43.6,
		"keeper_adv_Att__1": 832,
		"keeper_adv_Thr": 110,
		"keeper_adv_Launch%": 34.9,
		"keeper_adv_AvgLen": 35.8,
		"keeper_adv_Att__2": 240,
		"keeper_adv_Launch%__1": 57.9,
		"keeper_adv_AvgLen__1": 46.1,
		"keeper_adv_Opp": 244,
		"keeper_adv_Stp": 20,
		"keeper_adv_Stp%": 8.2,
		"keeper_adv_#OPA": 16,
		"keeper_adv_#OPA/90": 0.52,
		"keeper_adv_AvgDist": 14.2,
		"keeper_adv_Matches": "Matches"
	},
	"5": {
		"keeper_Player": "Claudio Bravo\\10072610",
		"keeper_Nation": "cl CHI",
		"keeper_Pos": "GK",
		"keeper_Squad": "Betis",
		"keeper_Age": 38,
		"keeper_Born": 1983,
		"keeper_MP": 17,
		"keeper_Starts": 17,
		"keeper_Min": 1456,
		"keeper_90s": 16.2,
		"keeper_GA": 19,
		"keeper_GA90": 1.17,
		"keeper_SoTA": 55,
		"keeper_Saves": 39,
		"keeper_Save%": 67.3,
		"keeper_W": 8,
		"keeper_D": 4,
		"keeper_L": 5,
		"keeper_CS": 5,
		"keeper_CS%": 29.4,
		"keeper_PKatt": 1,
		"keeper_PKA": 1,
		"keeper_PKsv": 0,
		"keeper_PKm": 0,
		"keeper_Save%__1": 0,
		"keeper_Matches": "Matches",
		"code": "10072610",
		"url": "/en/players/10072610/Claudio-Bravo",
		"keeper_adv_Player": "Claudio Bravo\\10072610",
		"keeper_adv_Nation": "cl CHI",
		"keeper_adv_Pos": "GK",
		"keeper_adv_Squad": "Betis",
		"keeper_adv_Age": 38,
		"keeper_adv_Born": 1983,
		"keeper_adv_90s": 16.2,
		"keeper_adv_GA": 19,
		"keeper_adv_PKA": 1,
		"keeper_adv_FK": 0,
		"keeper_adv_CK": 1,
		"keeper_adv_OG": 2,
		"keeper_adv_PSxG": 19.9,
		"keeper_adv_PSxG/SoT": 0.35,
		"keeper_adv_PSxG+/-": "+2.9",
		"keeper_adv_/90": "+0.18",
		"keeper_adv_Cmp": 114,
		"keeper_adv_Att": 286,
		"keeper_adv_Cmp%": 39.9,
		"keeper_adv_Att__1": 409,
		"keeper_adv_Thr": 51,
		"keeper_adv_Launch%": 54.3,
		"keeper_adv_AvgLen": 44.3,
		"keeper_adv_Att__2": 98,
		"keeper_adv_Launch%__1": 65.3,
		"keeper_adv_AvgLen__1": 51.1,
		"keeper_adv_Opp": 164,
		"keeper_adv_Stp": 4,
		"keeper_adv_Stp%": 2.4,
		"keeper_adv_#OPA": 8,
		"keeper_adv_#OPA/90": 0.49,
		"keeper_adv_AvgDist": 13.4,
		"keeper_adv_Matches": "Matches"
	},
	"6": {
		"keeper_Player": "Cárdenas\\e1846dde",
		"keeper_Nation": "es ESP",
		"keeper_Pos": "GK",
		"keeper_Squad": "Levante",
		"keeper_Age": 24,
		"keeper_Born": 1997,
		"keeper_MP": 24,
		"keeper_Starts": 24,
		"keeper_Min": 2160,
		"keeper_90s": 24,
		"keeper_GA": 46,
		"keeper_GA90": 1.92,
		"keeper_SoTA": 115,
		"keeper_Saves": 71,
		"keeper_Save%": 63.5,
		"keeper_W": 6,
		"keeper_D": 6,
		"keeper_L": 12,
		"keeper_CS": 5,
		"keeper_CS%": 20.8,
		"keeper_PKatt": 4,
		"keeper_PKA": 4,
		"keeper_PKsv": 0,
		"keeper_PKm": 0,
		"keeper_Save%__1": 0,
		"keeper_Matches": "Matches",
		"code": "e1846dde",
		"url": "/en/players/e1846dde/Cardenas",
		"keeper_adv_Player": "Cárdenas\\e1846dde",
		"keeper_adv_Nation": "es ESP",
		"keeper_adv_Pos": "GK",
		"keeper_adv_Squad": "Levante",
		"keeper_adv_Age": 24,
		"keeper_adv_Born": 1997,
		"keeper_adv_90s": 24,
		"keeper_adv_GA": 46,
		"keeper_adv_PKA": 4,
		"keeper_adv_FK": 1,
		"keeper_adv_CK": 7,
		"keeper_adv_OG": 0,
		"keeper_adv_PSxG": 41.7,
		"keeper_adv_PSxG/SoT": 0.33,
		"keeper_adv_PSxG+/-": -4.3,
		"keeper_adv_/90": -0.18,
		"keeper_adv_Cmp": 113,
		"keeper_adv_Att": 326,
		"keeper_adv_Cmp%": 34.7,
		"keeper_adv_Att__1": 526,
		"keeper_adv_Thr": 83,
		"keeper_adv_Launch%": 46.2,
		"keeper_adv_AvgLen": 40.1,
		"keeper_adv_Att__2": 193,
		"keeper_adv_Launch%__1": 43,
		"keeper_adv_AvgLen__1": 38.7,
		"keeper_adv_Opp": 235,
		"keeper_adv_Stp": 12,
		"keeper_adv_Stp%": 5.1,
		"keeper_adv_#OPA": 15,
		"keeper_adv_#OPA/90": 0.63,
		"keeper_adv_AvgDist": 13.9,
		"keeper_adv_Matches": "Matches"
	},
	"7": {
		"keeper_Player": "Kiko Casilla\\58bc7d18",
		"keeper_Nation": "es ESP",
		"keeper_Pos": "GK",
		"keeper_Squad": "Elche",
		"keeper_Age": 34,
		"keeper_Born": 1986,
		"keeper_MP": 14,
		"keeper_Starts": 14,
		"keeper_Min": 1260,
		"keeper_90s": 14,
		"keeper_GA": 17,
		"keeper_GA90": 1.21,
		"keeper_SoTA": 60,
		"keeper_Saves": 43,
		"keeper_Save%": 71.7,
		"keeper_W": 3,
		"keeper_D": 4,
		"keeper_L": 7,
		"keeper_CS": 3,
		"keeper_CS%": 21.4,
		"keeper_PKatt": 0,
		"keeper_PKA": 0,
		"keeper_PKsv": 0,
		"keeper_PKm": 0,
		"keeper_Save%__1": "",
		"keeper_Matches": "Matches",
		"code": "58bc7d18",
		"url": "/en/players/58bc7d18/Kiko-Casilla",
		"keeper_adv_Player": "Kiko Casilla\\58bc7d18",
		"keeper_adv_Nation": "es ESP",
		"keeper_adv_Pos": "GK",
		"keeper_adv_Squad": "Elche",
		"keeper_adv_Age": 34,
		"keeper_adv_Born": 1986,
		"keeper_adv_90s": 14,
		"keeper_adv_GA": 17,
		"keeper_adv_PKA": 0,
		"keeper_adv_FK": 0,
		"keeper_adv_CK": 1,
		"keeper_adv_OG": 0,
		"keeper_adv_PSxG": 16,
		"keeper_adv_PSxG/SoT": 0.27,
		"keeper_adv_PSxG+/-": -1,
		"keeper_adv_/90": -0.07,
		"keeper_adv_Cmp": 96,
		"keeper_adv_Att": 249,
		"keeper_adv_Cmp%": 38.6,
		"keeper_adv_Att__1": 346,
		"keeper_adv_Thr": 73,
		"keeper_adv_Launch%": 50.3,
		"keeper_adv_AvgLen": 40.4,
		"keeper_adv_Att__2": 135,
		"keeper_adv_Launch%__1": 55.6,
		"keeper_adv_AvgLen__1": 43.7,
		"keeper_adv_Opp": 130,
		"keeper_adv_Stp": 7,
		"keeper_adv_Stp%": 5.4,
		"keeper_adv_#OPA": 11,
		"keeper_adv_#OPA/90": 0.79,
		"keeper_adv_AvgDist": 15.4,
		"keeper_adv_Matches": "Matches"
	},
	"8": {
		"keeper_Player": "Jasper Cillessen\\04ac8285",
		"keeper_Nation": "nl NED",
		"keeper_Pos": "GK",
		"keeper_Squad": "Valencia",
		"keeper_Age": 32,
		"keeper_Born": 1989,
		"keeper_MP": 17,
		"keeper_Starts": 17,
		"keeper_Min": 1457,
		"keeper_90s": 16.2,
		"keeper_GA": 29,
		"keeper_GA90": 1.79,
		"keeper_SoTA": 71,
		"keeper_Saves": 47,
		"keeper_Save%": 66.2,
		"keeper_W": 4,
		"keeper_D": 8,
		"keeper_L": 5,
		"keeper_CS": 3,
		"keeper_CS%": 17.6,
		"keeper_PKatt": 6,
		"keeper_PKA": 5,
		"keeper_PKsv": 1,
		"keeper_PKm": 0,
		"keeper_Save%__1": 16.7,
		"keeper_Matches": "Matches",
		"code": "04ac8285",
		"url": "/en/players/04ac8285/Jasper-Cillessen",
		"keeper_adv_Player": "Jasper Cillessen\\04ac8285",
		"keeper_adv_Nation": "nl NED",
		"keeper_adv_Pos": "GK",
		"keeper_adv_Squad": "Valencia",
		"keeper_adv_Age": 32,
		"keeper_adv_Born": 1989,
		"keeper_adv_90s": 16.2,
		"keeper_adv_GA": 29,
		"keeper_adv_PKA": 5,
		"keeper_adv_FK": 0,
		"keeper_adv_CK": 4,
		"keeper_adv_OG": 2,
		"keeper_adv_PSxG": 29,
		"keeper_adv_PSxG/SoT": 0.36,
		"keeper_adv_PSxG+/-": "+2.0",
		"keeper_adv_/90": "+0.12",
		"keeper_adv_Cmp": 112,
		"keeper_adv_Att": 260,
		"keeper_adv_Cmp%": 43.1,
		"keeper_adv_Att__1": 347,
		"keeper_adv_Thr": 69,
		"keeper_adv_Launch%": 53.9,
		"keeper_adv_AvgLen": 45.3,
		"keeper_adv_Att__2": 99,
		"keeper_adv_Launch%__1": 73.7,
		"keeper_adv_AvgLen__1": 57,
		"keeper_adv_Opp": 122,
		"keeper_adv_Stp": 11,
		"keeper_adv_Stp%": 9,
		"keeper_adv_#OPA": 8,
		"keeper_adv_#OPA/90": 0.49,
		"keeper_adv_AvgDist": 15.3,
		"keeper_adv_Matches": "Matches"
	},
	"9": {
		"keeper_Player": "Diego Conde\\4eae5bc4",
		"keeper_Nation": "es ESP",
		"keeper_Pos": "GK",
		"keeper_Squad": "Getafe",
		"keeper_Age": 22,
		"keeper_Born": 1998,
		"keeper_MP": 1,
		"keeper_Starts": 0,
		"keeper_Min": 6,
		"keeper_90s": 0.1,
		"keeper_GA": 0,
		"keeper_GA90": 0,
		"keeper_SoTA": 0,
		"keeper_Saves": 0,
		"keeper_Save%": "",
		"keeper_W": 0,
		"keeper_D": 0,
		"keeper_L": 0,
		"keeper_CS": 1,
		"keeper_CS%": "",
		"keeper_PKatt": 0,
		"keeper_PKA": 0,
		"keeper_PKsv": 0,
		"keeper_PKm": 0,
		"keeper_Save%__1": "",
		"keeper_Matches": "Matches",
		"code": "4eae5bc4",
		"url": "/en/players/4eae5bc4/Diego-Conde",
		"keeper_adv_Player": "Diego Conde\\4eae5bc4",
		"keeper_adv_Nation": "es ESP",
		"keeper_adv_Pos": "GK",
		"keeper_adv_Squad": "Getafe",
		"keeper_adv_Age": 22,
		"keeper_adv_Born": 1998,
		"keeper_adv_90s": 0.1,
		"keeper_adv_GA": 0,
		"keeper_adv_PKA": 0,
		"keeper_adv_FK": 0,
		"keeper_adv_CK": 0,
		"keeper_adv_OG": 0,
		"keeper_adv_PSxG": 0,
		"keeper_adv_PSxG/SoT": "",
		"keeper_adv_PSxG+/-": 0,
		"keeper_adv_/90": 0,
		"keeper_adv_Cmp": 0,
		"keeper_adv_Att": 6,
		"keeper_adv_Cmp%": 0,
		"keeper_adv_Att__1": 4,
		"keeper_adv_Thr": 0,
		"keeper_adv_Launch%": 100,
		"keeper_adv_AvgLen": 65.3,
		"keeper_adv_Att__2": 2,
		"keeper_adv_Launch%__1": 100,
		"keeper_adv_AvgLen__1": 68.5,
		"keeper_adv_Opp": 2,
		"keeper_adv_Stp": 0,
		"keeper_adv_Stp%": 0,
		"keeper_adv_#OPA": 0,
		"keeper_adv_#OPA/90": 0,
		"keeper_adv_AvgDist": "",
		"keeper_adv_Matches": "Matches"
	},
	"10": {
		"keeper_Player": "Thibaut Courtois\\1840e36d",
		"keeper_Nation": "be BEL",
		"keeper_Pos": "GK",
		"keeper_Squad": "Real Madrid",
		"keeper_Age": 29,
		"keeper_Born": 1992,
		"keeper_MP": 36,
		"keeper_Starts": 36,
		"keeper_Min": 3240,
		"keeper_90s": 36,
		"keeper_GA": 29,
		"keeper_GA90": 0.81,
		"keeper_SoTA": 116,
		"keeper_Saves": 88,
		"keeper_Save%": 76.7,
		"keeper_W": 26,
		"keeper_D": 7,
		"keeper_L": 3,
		"keeper_CS": 16,
		"keeper_CS%": 44.4,
		"keeper_PKatt": 3,
		"keeper_PKA": 2,
		"keeper_PKsv": 1,
		"keeper_PKm": 0,
		"keeper_Save%__1": 33.3,
		"keeper_Matches": "Matches",
		"code": "1840e36d",
		"url": "/en/players/1840e36d/Thibaut-Courtois",
		"keeper_adv_Player": "Thibaut Courtois\\1840e36d",
		"keeper_adv_Nation": "be BEL",
		"keeper_adv_Pos": "GK",
		"keeper_adv_Squad": "Real Madrid",
		"keeper_adv_Age": 29,
		"keeper_adv_Born": 1992,
		"keeper_adv_90s": 36,
		"keeper_adv_GA": 29,
		"keeper_adv_PKA": 2,
		"keeper_adv_FK": 1,
		"keeper_adv_CK": 2,
		"keeper_adv_OG": 0,
		"keeper_adv_PSxG": 33.9,
		"keeper_adv_PSxG/SoT": 0.27,
		"keeper_adv_PSxG+/-": "+4.9",
		"keeper_adv_/90": "+0.14",
		"keeper_adv_Cmp": 114,
		"keeper_adv_Att": 306,
		"keeper_adv_Cmp%": 37.3,
		"keeper_adv_Att__1": 929,
		"keeper_adv_Thr": 188,
		"keeper_adv_Launch%": 23.5,
		"keeper_adv_AvgLen": 31.2,
		"keeper_adv_Att__2": 210,
		"keeper_adv_Launch%__1": 41.9,
		"keeper_adv_AvgLen__1": 39.1,
		"keeper_adv_Opp": 312,
		"keeper_adv_Stp": 27,
		"keeper_adv_Stp%": 8.7,
		"keeper_adv_#OPA": 21,
		"keeper_adv_#OPA/90": 0.58,
		"keeper_adv_AvgDist": 14.2,
		"keeper_adv_Matches": "Matches"
	},
	"11": {
		"keeper_Player": "Javier Díaz\\17a1299d",
		"keeper_Nation": "es ESP",
		"keeper_Pos": "GK",
		"keeper_Squad": "Sevilla",
		"keeper_Age": 24,
		"keeper_Born": 1997,
		"keeper_MP": 1,
		"keeper_Starts": 1,
		"keeper_Min": 90,
		"keeper_90s": 1,
		"keeper_GA": 1,
		"keeper_GA90": 1,
		"keeper_SoTA": 2,
		"keeper_Saves": 1,
		"keeper_Save%": 50,
		"keeper_W": 0,
		"keeper_D": 1,
		"keeper_L": 0,
		"keeper_CS": 0,
		"keeper_CS%": 0,
		"keeper_PKatt": 0,
		"keeper_PKA": 0,
		"keeper_PKsv": 0,
		"keeper_PKm": 0,
		"keeper_Save%__1": "",
		"keeper_Matches": "Matches",
		"code": "17a1299d",
		"url": "/en/players/17a1299d/Javier-Diaz",
		"keeper_adv_Player": "Javier Díaz\\17a1299d",
		"keeper_adv_Nation": "es ESP",
		"keeper_adv_Pos": "GK",
		"keeper_adv_Squad": "Sevilla",
		"keeper_adv_Age": 24,
		"keeper_adv_Born": 1997,
		"keeper_adv_90s": 1,
		"keeper_adv_GA": 1,
		"keeper_adv_PKA": 0,
		"keeper_adv_FK": 0,
		"keeper_adv_CK": 0,
		"keeper_adv_OG": 0,
		"keeper_adv_PSxG": 0.3,
		"keeper_adv_PSxG/SoT": 0.15,
		"keeper_adv_PSxG+/-": -0.7,
		"keeper_adv_/90": -0.7,
		"keeper_adv_Cmp": 5,
		"keeper_adv_Att": 10,
		"keeper_adv_Cmp%": 50,
		"keeper_adv_Att__1": 30,
		"keeper_adv_Thr": 2,
		"keeper_adv_Launch%": 26.7,
		"keeper_adv_AvgLen": 31.9,
		"keeper_adv_Att__2": 3,
		"keeper_adv_Launch%__1": 66.7,
		"keeper_adv_AvgLen__1": 50.3,
		"keeper_adv_Opp": 12,
		"keeper_adv_Stp": 1,
		"keeper_adv_Stp%": 8.3,
		"keeper_adv_#OPA": 1,
		"keeper_adv_#OPA/90": 1,
		"keeper_adv_AvgDist": 25,
		"keeper_adv_Matches": "Matches"
	},
	"12": {
		"keeper_Player": "Stole Dimitrievski\\fc70e345",
		"keeper_Nation": "mk MKD",
		"keeper_Pos": "GK",
		"keeper_Squad": "Rayo Vallecano",
		"keeper_Age": 27,
		"keeper_Born": 1993,
		"keeper_MP": 31,
		"keeper_Starts": 30,
		"keeper_Min": 2772,
		"keeper_90s": 30.8,
		"keeper_GA": 37,
		"keeper_GA90": 1.2,
		"keeper_SoTA": 116,
		"keeper_Saves": 86,
		"keeper_Save%": 74.1,
		"keeper_W": 11,
		"keeper_D": 8,
		"keeper_L": 11,
		"keeper_CS": 9,
		"keeper_CS%": 30,
		"keeper_PKatt": 9,
		"keeper_PKA": 7,
		"keeper_PKsv": 2,
		"keeper_PKm": 0,
		"keeper_Save%__1": 22.2,
		"keeper_Matches": "Matches",
		"code": "fc70e345",
		"url": "/en/players/fc70e345/Stole-Dimitrievski",
		"keeper_adv_Player": "Stole Dimitrievski\\fc70e345",
		"keeper_adv_Nation": "mk MKD",
		"keeper_adv_Pos": "GK",
		"keeper_adv_Squad": "Rayo Vallecano",
		"keeper_adv_Age": 27,
		"keeper_adv_Born": 1993,
		"keeper_adv_90s": 30.8,
		"keeper_adv_GA": 37,
		"keeper_adv_PKA": 7,
		"keeper_adv_FK": 0,
		"keeper_adv_CK": 5,
		"keeper_adv_OG": 1,
		"keeper_adv_PSxG": 39,
		"keeper_adv_PSxG/SoT": 0.27,
		"keeper_adv_PSxG+/-": "+3.0",
		"keeper_adv_/90": "+0.10",
		"keeper_adv_Cmp": 207,
		"keeper_adv_Att": 611,
		"keeper_adv_Cmp%": 33.9,
		"keeper_adv_Att__1": 726,
		"keeper_adv_Thr": 148,
		"keeper_adv_Launch%": 59.8,
		"keeper_adv_AvgLen": 47.5,
		"keeper_adv_Att__2": 229,
		"keeper_adv_Launch%__1": 77.3,
		"keeper_adv_AvgLen__1": 58.1,
		"keeper_adv_Opp": 251,
		"keeper_adv_Stp": 24,
		"keeper_adv_Stp%": 9.6,
		"keeper_adv_#OPA": 17,
		"keeper_adv_#OPA/90": 0.55,
		"keeper_adv_AvgDist": 12.9,
		"keeper_adv_Matches": "Matches"
	},
	"13": {
		"keeper_Player": "Matías Dituro\\b6160ad0",
		"keeper_Nation": "ar ARG",
		"keeper_Pos": "GK",
		"keeper_Squad": "Celta Vigo",
		"keeper_Age": 34,
		"keeper_Born": 1987,
		"keeper_MP": 38,
		"keeper_Starts": 38,
		"keeper_Min": 3420,
		"keeper_90s": 38,
		"keeper_GA": 43,
		"keeper_GA90": 1.13,
		"keeper_SoTA": 128,
		"keeper_Saves": 91,
		"keeper_Save%": 69.5,
		"keeper_W": 12,
		"keeper_D": 10,
		"keeper_L": 16,
		"keeper_CS": 14,
		"keeper_CS%": 36.8,
		"keeper_PKatt": 8,
		"keeper_PKA": 4,
		"keeper_PKsv": 4,
		"keeper_PKm": 0,
		"keeper_Save%__1": 50,
		"keeper_Matches": "Matches",
		"code": "b6160ad0",
		"url": "/en/players/b6160ad0/Matias-Dituro",
		"keeper_adv_Player": "Matías Dituro\\b6160ad0",
		"keeper_adv_Nation": "ar ARG",
		"keeper_adv_Pos": "GK",
		"keeper_adv_Squad": "Celta Vigo",
		"keeper_adv_Age": 34,
		"keeper_adv_Born": 1987,
		"keeper_adv_90s": 38,
		"keeper_adv_GA": 43,
		"keeper_adv_PKA": 4,
		"keeper_adv_FK": 0,
		"keeper_adv_CK": 1,
		"keeper_adv_OG": 2,
		"keeper_adv_PSxG": 47,
		"keeper_adv_PSxG/SoT": 0.32,
		"keeper_adv_PSxG+/-": "+6.0",
		"keeper_adv_/90": "+0.16",
		"keeper_adv_Cmp": 349,
		"keeper_adv_Att": 859,
		"keeper_adv_Cmp%": 40.6,
		"keeper_adv_Att__1": 1177,
		"keeper_adv_Thr": 129,
		"keeper_adv_Launch%": 55.1,
		"keeper_adv_AvgLen": 44.5,
		"keeper_adv_Att__2": 283,
		"keeper_adv_Launch%__1": 74.2,
		"keeper_adv_AvgLen__1": 56,
		"keeper_adv_Opp": 299,
		"keeper_adv_Stp": 44,
		"keeper_adv_Stp%": 14.7,
		"keeper_adv_#OPA": 33,
		"keeper_adv_#OPA/90": 0.87,
		"keeper_adv_AvgDist": 15.6,
		"keeper_adv_Matches": "Matches"
	},
	"14": {
		"keeper_Player": "Marko Dmitrović\\ac295d9e",
		"keeper_Nation": "rs SRB",
		"keeper_Pos": "GK",
		"keeper_Squad": "Sevilla",
		"keeper_Age": 29,
		"keeper_Born": 1992,
		"keeper_MP": 6,
		"keeper_Starts": 6,
		"keeper_Min": 540,
		"keeper_90s": 6,
		"keeper_GA": 5,
		"keeper_GA90": 0.83,
		"keeper_SoTA": 18,
		"keeper_Saves": 13,
		"keeper_Save%": 72.2,
		"keeper_W": 4,
		"keeper_D": 2,
		"keeper_L": 0,
		"keeper_CS": 4,
		"keeper_CS%": 66.7,
		"keeper_PKatt": 0,
		"keeper_PKA": 0,
		"keeper_PKsv": 0,
		"keeper_PKm": 0,
		"keeper_Save%__1": "",
		"keeper_Matches": "Matches",
		"code": "ac295d9e",
		"url": "/en/players/ac295d9e/Marko-Dmitrovic",
		"keeper_adv_Player": "Marko Dmitrović\\ac295d9e",
		"keeper_adv_Nation": "rs SRB",
		"keeper_adv_Pos": "GK",
		"keeper_adv_Squad": "Sevilla",
		"keeper_adv_Age": 29,
		"keeper_adv_Born": 1992,
		"keeper_adv_90s": 6,
		"keeper_adv_GA": 5,
		"keeper_adv_PKA": 0,
		"keeper_adv_FK": 0,
		"keeper_adv_CK": 0,
		"keeper_adv_OG": 0,
		"keeper_adv_PSxG": 5.3,
		"keeper_adv_PSxG/SoT": 0.3,
		"keeper_adv_PSxG+/-": "+0.3",
		"keeper_adv_/90": "+0.04",
		"keeper_adv_Cmp": 28,
		"keeper_adv_Att": 63,
		"keeper_adv_Cmp%": 44.4,
		"keeper_adv_Att__1": 191,
		"keeper_adv_Thr": 25,
		"keeper_adv_Launch%": 26.7,
		"keeper_adv_AvgLen": 32.3,
		"keeper_adv_Att__2": 33,
		"keeper_adv_Launch%__1": 36.4,
		"keeper_adv_AvgLen__1": 36.6,
		"keeper_adv_Opp": 51,
		"keeper_adv_Stp": 4,
		"keeper_adv_Stp%": 7.8,
		"keeper_adv_#OPA": 9,
		"keeper_adv_#OPA/90": 1.5,
		"keeper_adv_AvgDist": 17.2,
		"keeper_adv_Matches": "Matches"
	},
	"15": {
		"keeper_Player": "Jaume Doménech\\c9cb972b",
		"keeper_Nation": "es ESP",
		"keeper_Pos": "GK",
		"keeper_Squad": "Valencia",
		"keeper_Age": 30,
		"keeper_Born": 1990,
		"keeper_MP": 4,
		"keeper_Starts": 3,
		"keeper_Min": 343,
		"keeper_90s": 3.8,
		"keeper_GA": 4,
		"keeper_GA90": 1.05,
		"keeper_SoTA": 11,
		"keeper_Saves": 8,
		"keeper_Save%": 63.6,
		"keeper_W": 2,
		"keeper_D": 0,
		"keeper_L": 1,
		"keeper_CS": 1,
		"keeper_CS%": 33.3,
		"keeper_PKatt": 0,
		"keeper_PKA": 0,
		"keeper_PKsv": 0,
		"keeper_PKm": 0,
		"keeper_Save%__1": "",
		"keeper_Matches": "Matches",
		"code": "c9cb972b",
		"url": "/en/players/c9cb972b/Jaume-Domenech",
		"keeper_adv_Player": "Jaume Doménech\\c9cb972b",
		"keeper_adv_Nation": "es ESP",
		"keeper_adv_Pos": "GK",
		"keeper_adv_Squad": "Valencia",
		"keeper_adv_Age": 30,
		"keeper_adv_Born": 1990,
		"keeper_adv_90s": 3.8,
		"keeper_adv_GA": 4,
		"keeper_adv_PKA": 0,
		"keeper_adv_FK": 0,
		"keeper_adv_CK": 1,
		"keeper_adv_OG": 1,
		"keeper_adv_PSxG": 4.8,
		"keeper_adv_PSxG/SoT": 0.43,
		"keeper_adv_PSxG+/-": "+1.8",
		"keeper_adv_/90": "+0.47",
		"keeper_adv_Cmp": 39,
		"keeper_adv_Att": 79,
		"keeper_adv_Cmp%": 49.4,
		"keeper_adv_Att__1": 75,
		"keeper_adv_Thr": 8,
		"keeper_adv_Launch%": 72,
		"keeper_adv_AvgLen": 48.1,
		"keeper_adv_Att__2": 32,
		"keeper_adv_Launch%__1": 78.1,
		"keeper_adv_AvgLen__1": 56,
		"keeper_adv_Opp": 40,
		"keeper_adv_Stp": 3,
		"keeper_adv_Stp%": 7.5,
		"keeper_adv_#OPA": 1,
		"keeper_adv_#OPA/90": 0.26,
		"keeper_adv_AvgDist": 10.5,
		"keeper_adv_Matches": "Matches"
	},
	"16": {
		"keeper_Player": "Aarón Escandell\\67669ce7",
		"keeper_Nation": "es ESP",
		"keeper_Pos": "GK",
		"keeper_Squad": "Granada",
		"keeper_Age": 25,
		"keeper_Born": 1995,
		"keeper_MP": 4,
		"keeper_Starts": 3,
		"keeper_Min": 284,
		"keeper_90s": 3.2,
		"keeper_GA": 6,
		"keeper_GA90": 1.9,
		"keeper_SoTA": 14,
		"keeper_Saves": 10,
		"keeper_Save%": 71.4,
		"keeper_W": 0,
		"keeper_D": 2,
		"keeper_L": 1,
		"keeper_CS": 1,
		"keeper_CS%": 33.3,
		"keeper_PKatt": 2,
		"keeper_PKA": 2,
		"keeper_PKsv": 0,
		"keeper_PKm": 0,
		"keeper_Save%__1": 0,
		"keeper_Matches": "Matches",
		"code": "67669ce7",
		"url": "/en/players/67669ce7/Aaron-Escandell",
		"keeper_adv_Player": "Aarón Escandell\\67669ce7",
		"keeper_adv_Nation": "es ESP",
		"keeper_adv_Pos": "GK",
		"keeper_adv_Squad": "Granada",
		"keeper_adv_Age": 25,
		"keeper_adv_Born": 1995,
		"keeper_adv_90s": 3.2,
		"keeper_adv_GA": 6,
		"keeper_adv_PKA": 2,
		"keeper_adv_FK": 0,
		"keeper_adv_CK": 0,
		"keeper_adv_OG": 0,
		"keeper_adv_PSxG": 4.2,
		"keeper_adv_PSxG/SoT": 0.19,
		"keeper_adv_PSxG+/-": -1.8,
		"keeper_adv_/90": -0.58,
		"keeper_adv_Cmp": 39,
		"keeper_adv_Att": 89,
		"keeper_adv_Cmp%": 43.8,
		"keeper_adv_Att__1": 88,
		"keeper_adv_Thr": 13,
		"keeper_adv_Launch%": 68.2,
		"keeper_adv_AvgLen": 48.1,
		"keeper_adv_Att__2": 37,
		"keeper_adv_Launch%__1": 78.4,
		"keeper_adv_AvgLen__1": 54.3,
		"keeper_adv_Opp": 26,
		"keeper_adv_Stp": 2,
		"keeper_adv_Stp%": 7.7,
		"keeper_adv_#OPA": 7,
		"keeper_adv_#OPA/90": 2.22,
		"keeper_adv_AvgDist": 14.5,
		"keeper_adv_Matches": "Matches"
	},
	"17": {
		"keeper_Player": "Aitor Fernández\\a01c3d54",
		"keeper_Nation": "es ESP",
		"keeper_Pos": "GK",
		"keeper_Squad": "Levante",
		"keeper_Age": 30,
		"keeper_Born": 1991,
		"keeper_MP": 13,
		"keeper_Starts": 13,
		"keeper_Min": 1166,
		"keeper_90s": 13,
		"keeper_GA": 29,
		"keeper_GA90": 2.24,
		"keeper_SoTA": 79,
		"keeper_Saves": 51,
		"keeper_Save%": 64.6,
		"keeper_W": 1,
		"keeper_D": 5,
		"keeper_L": 7,
		"keeper_CS": 2,
		"keeper_CS%": 15.4,
		"keeper_PKatt": 2,
		"keeper_PKA": 1,
		"keeper_PKsv": 1,
		"keeper_PKm": 0,
		"keeper_Save%__1": 50,
		"keeper_Matches": "Matches",
		"code": "a01c3d54",
		"url": "/en/players/a01c3d54/Aitor-Fernandez",
		"keeper_adv_Player": "Aitor Fernández\\a01c3d54",
		"keeper_adv_Nation": "es ESP",
		"keeper_adv_Pos": "GK",
		"keeper_adv_Squad": "Levante",
		"keeper_adv_Age": 30,
		"keeper_adv_Born": 1991,
		"keeper_adv_90s": 13,
		"keeper_adv_GA": 29,
		"keeper_adv_PKA": 1,
		"keeper_adv_FK": 0,
		"keeper_adv_CK": 8,
		"keeper_adv_OG": 0,
		"keeper_adv_PSxG": 24.9,
		"keeper_adv_PSxG/SoT": 0.29,
		"keeper_adv_PSxG+/-": -4.1,
		"keeper_adv_/90": -0.32,
		"keeper_adv_Cmp": 73,
		"keeper_adv_Att": 174,
		"keeper_adv_Cmp%": 42,
		"keeper_adv_Att__1": 290,
		"keeper_adv_Thr": 62,
		"keeper_adv_Launch%": 46.2,
		"keeper_adv_AvgLen": 40.2,
		"keeper_adv_Att__2": 91,
		"keeper_adv_Launch%__1": 44,
		"keeper_adv_AvgLen__1": 36.4,
		"keeper_adv_Opp": 111,
		"keeper_adv_Stp": 5,
		"keeper_adv_Stp%": 4.5,
		"keeper_adv_#OPA": 11,
		"keeper_adv_#OPA/90": 0.85,
		"keeper_adv_AvgDist": 16.3,
		"keeper_adv_Matches": "Matches"
	},
	"18": {
		"keeper_Player": "Joan García\\87b498b0",
		"keeper_Nation": "es ESP",
		"keeper_Pos": "GK",
		"keeper_Squad": "Espanyol",
		"keeper_Age": 20,
		"keeper_Born": 2001,
		"keeper_MP": 2,
		"keeper_Starts": 1,
		"keeper_Min": 108,
		"keeper_90s": 1.2,
		"keeper_GA": 3,
		"keeper_GA90": 2.5,
		"keeper_SoTA": 3,
		"keeper_Saves": 0,
		"keeper_Save%": 0,
		"keeper_W": 0,
		"keeper_D": 0,
		"keeper_L": 1,
		"keeper_CS": 0,
		"keeper_CS%": 0,
		"keeper_PKatt": 0,
		"keeper_PKA": 0,
		"keeper_PKsv": 0,
		"keeper_PKm": 0,
		"keeper_Save%__1": "",
		"keeper_Matches": "Matches",
		"code": "87b498b0",
		"url": "/en/players/87b498b0/Joan-Garcia",
		"keeper_adv_Player": "Joan García\\87b498b0",
		"keeper_adv_Nation": "es ESP",
		"keeper_adv_Pos": "GK",
		"keeper_adv_Squad": "Espanyol",
		"keeper_adv_Age": 20,
		"keeper_adv_Born": 2001,
		"keeper_adv_90s": 1.2,
		"keeper_adv_GA": 3,
		"keeper_adv_PKA": 0,
		"keeper_adv_FK": 0,
		"keeper_adv_CK": 0,
		"keeper_adv_OG": 0,
		"keeper_adv_PSxG": 1.2,
		"keeper_adv_PSxG/SoT": 0.39,
		"keeper_adv_PSxG+/-": -1.8,
		"keeper_adv_/90": -1.53,
		"keeper_adv_Cmp": 4,
		"keeper_adv_Att": 12,
		"keeper_adv_Cmp%": 33.3,
		"keeper_adv_Att__1": 31,
		"keeper_adv_Thr": 9,
		"keeper_adv_Launch%": 32.3,
		"keeper_adv_AvgLen": 31.4,
		"keeper_adv_Att__2": 2,
		"keeper_adv_Launch%__1": 100,
		"keeper_adv_AvgLen__1": 71.5,
		"keeper_adv_Opp": 11,
		"keeper_adv_Stp": 2,
		"keeper_adv_Stp%": 18.2,
		"keeper_adv_#OPA": 2,
		"keeper_adv_#OPA/90": 1.67,
		"keeper_adv_AvgDist": 18.6,
		"keeper_adv_Matches": "Matches"
	},
	"19": {
		"keeper_Player": "Dominik Greif\\30061f53",
		"keeper_Nation": "sk SVK",
		"keeper_Pos": "GK",
		"keeper_Squad": "Mallorca",
		"keeper_Age": 24,
		"keeper_Born": 1997,
		"keeper_MP": 1,
		"keeper_Starts": 1,
		"keeper_Min": 90,
		"keeper_90s": 1,
		"keeper_GA": 3,
		"keeper_GA90": 3,
		"keeper_SoTA": 6,
		"keeper_Saves": 3,
		"keeper_Save%": 50,
		"keeper_W": 0,
		"keeper_D": 0,
		"keeper_L": 1,
		"keeper_CS": 0,
		"keeper_CS%": 0,
		"keeper_PKatt": 0,
		"keeper_PKA": 0,
		"keeper_PKsv": 0,
		"keeper_PKm": 0,
		"keeper_Save%__1": "",
		"keeper_Matches": "Matches",
		"code": "30061f53",
		"url": "/en/players/30061f53/Dominik-Greif",
		"keeper_adv_Player": "Dominik Greif\\30061f53",
		"keeper_adv_Nation": "sk SVK",
		"keeper_adv_Pos": "GK",
		"keeper_adv_Squad": "Mallorca",
		"keeper_adv_Age": 24,
		"keeper_adv_Born": 1997,
		"keeper_adv_90s": 1,
		"keeper_adv_GA": 3,
		"keeper_adv_PKA": 0,
		"keeper_adv_FK": 1,
		"keeper_adv_CK": 0,
		"keeper_adv_OG": 0,
		"keeper_adv_PSxG": 1.1,
		"keeper_adv_PSxG/SoT": 0.19,
		"keeper_adv_PSxG+/-": -1.9,
		"keeper_adv_/90": -1.87,
		"keeper_adv_Cmp": 2,
		"keeper_adv_Att": 13,
		"keeper_adv_Cmp%": 15.4,
		"keeper_adv_Att__1": 21,
		"keeper_adv_Thr": 6,
		"keeper_adv_Launch%": 42.9,
		"keeper_adv_AvgLen": 37.8,
		"keeper_adv_Att__2": 10,
		"keeper_adv_Launch%__1": 40,
		"keeper_adv_AvgLen__1": 37.4,
		"keeper_adv_Opp": 8,
		"keeper_adv_Stp": 0,
		"keeper_adv_Stp%": 0,
		"keeper_adv_#OPA": 1,
		"keeper_adv_#OPA/90": 1,
		"keeper_adv_AvgDist": 13,
		"keeper_adv_Matches": "Matches"
	},
	"20": {
		"keeper_Player": "Sergio Herrera\\a4995f48",
		"keeper_Nation": "es ESP",
		"keeper_Pos": "GK",
		"keeper_Squad": "Osasuna",
		"keeper_Age": 28,
		"keeper_Born": 1993,
		"keeper_MP": 36,
		"keeper_Starts": 36,
		"keeper_Min": 3240,
		"keeper_90s": 36,
		"keeper_GA": 48,
		"keeper_GA90": 1.33,
		"keeper_SoTA": 136,
		"keeper_Saves": 92,
		"keeper_Save%": 67.6,
		"keeper_W": 12,
		"keeper_D": 10,
		"keeper_L": 14,
		"keeper_CS": 12,
		"keeper_CS%": 33.3,
		"keeper_PKatt": 7,
		"keeper_PKA": 4,
		"keeper_PKsv": 3,
		"keeper_PKm": 0,
		"keeper_Save%__1": 42.9,
		"keeper_Matches": "Matches",
		"code": "a4995f48",
		"url": "/en/players/a4995f48/Sergio-Herrera",
		"keeper_adv_Player": "Sergio Herrera\\a4995f48",
		"keeper_adv_Nation": "es ESP",
		"keeper_adv_Pos": "GK",
		"keeper_adv_Squad": "Osasuna",
		"keeper_adv_Age": 28,
		"keeper_adv_Born": 1993,
		"keeper_adv_90s": 36,
		"keeper_adv_GA": 48,
		"keeper_adv_PKA": 4,
		"keeper_adv_FK": 0,
		"keeper_adv_CK": 10,
		"keeper_adv_OG": 1,
		"keeper_adv_PSxG": 44.8,
		"keeper_adv_PSxG/SoT": 0.3,
		"keeper_adv_PSxG+/-": -2.2,
		"keeper_adv_/90": -0.06,
		"keeper_adv_Cmp": 411,
		"keeper_adv_Att": 881,
		"keeper_adv_Cmp%": 46.7,
		"keeper_adv_Att__1": 844,
		"keeper_adv_Thr": 75,
		"keeper_adv_Launch%": 73,
		"keeper_adv_AvgLen": 53,
		"keeper_adv_Att__2": 303,
		"keeper_adv_Launch%__1": 87.5,
		"keeper_adv_AvgLen__1": 62.4,
		"keeper_adv_Opp": 370,
		"keeper_adv_Stp": 21,
		"keeper_adv_Stp%": 5.7,
		"keeper_adv_#OPA": 43,
		"keeper_adv_#OPA/90": 1.19,
		"keeper_adv_AvgDist": 15.6,
		"keeper_adv_Matches": "Matches"
	},
	"21": {
		"keeper_Player": "Jeremías Ledesma\\6c4776b1",
		"keeper_Nation": "ar ARG",
		"keeper_Pos": "GK",
		"keeper_Squad": "Cádiz",
		"keeper_Age": 28,
		"keeper_Born": 1993,
		"keeper_MP": 38,
		"keeper_Starts": 38,
		"keeper_Min": 3420,
		"keeper_90s": 38,
		"keeper_GA": 51,
		"keeper_GA90": 1.34,
		"keeper_SoTA": 159,
		"keeper_Saves": 117,
		"keeper_Save%": 74.8,
		"keeper_W": 8,
		"keeper_D": 15,
		"keeper_L": 15,
		"keeper_CS": 13,
		"keeper_CS%": 34.2,
		"keeper_PKatt": 13,
		"keeper_PKA": 11,
		"keeper_PKsv": 2,
		"keeper_PKm": 0,
		"keeper_Save%__1": 15.4,
		"keeper_Matches": "Matches",
		"code": "6c4776b1",
		"url": "/en/players/6c4776b1/Jeremias-Ledesma",
		"keeper_adv_Player": "Jeremías Ledesma\\6c4776b1",
		"keeper_adv_Nation": "ar ARG",
		"keeper_adv_Pos": "GK",
		"keeper_adv_Squad": "Cádiz",
		"keeper_adv_Age": 28,
		"keeper_adv_Born": 1993,
		"keeper_adv_90s": 38,
		"keeper_adv_GA": 51,
		"keeper_adv_PKA": 11,
		"keeper_adv_FK": 0,
		"keeper_adv_CK": 10,
		"keeper_adv_OG": 0,
		"keeper_adv_PSxG": 52.1,
		"keeper_adv_PSxG/SoT": 0.26,
		"keeper_adv_PSxG+/-": "+1.1",
		"keeper_adv_/90": "+0.03",
		"keeper_adv_Cmp": 302,
		"keeper_adv_Att": 834,
		"keeper_adv_Cmp%": 36.2,
		"keeper_adv_Att__1": 846,
		"keeper_adv_Thr": 116,
		"keeper_adv_Launch%": 68,
		"keeper_adv_AvgLen": 52.1,
		"keeper_adv_Att__2": 310,
		"keeper_adv_Launch%__1": 83.5,
		"keeper_adv_AvgLen__1": 64.2,
		"keeper_adv_Opp": 368,
		"keeper_adv_Stp": 33,
		"keeper_adv_Stp%": 9,
		"keeper_adv_#OPA": 23,
		"keeper_adv_#OPA/90": 0.61,
		"keeper_adv_AvgDist": 13.7,
		"keeper_adv_Matches": "Matches"
	},
	"22": {
		"keeper_Player": "Diego López\\73683fa9",
		"keeper_Nation": "es ESP",
		"keeper_Pos": "GK",
		"keeper_Squad": "Espanyol",
		"keeper_Age": 39,
		"keeper_Born": 1981,
		"keeper_MP": 36,
		"keeper_Starts": 36,
		"keeper_Min": 3177,
		"keeper_90s": 35.3,
		"keeper_GA": 49,
		"keeper_GA90": 1.39,
		"keeper_SoTA": 152,
		"keeper_Saves": 106,
		"keeper_Save%": 69.7,
		"keeper_W": 10,
		"keeper_D": 12,
		"keeper_L": 14,
		"keeper_CS": 10,
		"keeper_CS%": 27.8,
		"keeper_PKatt": 4,
		"keeper_PKA": 3,
		"keeper_PKsv": 0,
		"keeper_PKm": 1,
		"keeper_Save%__1": 0,
		"keeper_Matches": "Matches",
		"code": "73683fa9",
		"url": "/en/players/73683fa9/Diego-Lopez",
		"keeper_adv_Player": "Diego López\\73683fa9",
		"keeper_adv_Nation": "es ESP",
		"keeper_adv_Pos": "GK",
		"keeper_adv_Squad": "Espanyol",
		"keeper_adv_Age": 39,
		"keeper_adv_Born": 1981,
		"keeper_adv_90s": 35.3,
		"keeper_adv_GA": 49,
		"keeper_adv_PKA": 3,
		"keeper_adv_FK": 0,
		"keeper_adv_CK": 4,
		"keeper_adv_OG": 2,
		"keeper_adv_PSxG": 45.4,
		"keeper_adv_PSxG/SoT": 0.28,
		"keeper_adv_PSxG+/-": -1.6,
		"keeper_adv_/90": -0.05,
		"keeper_adv_Cmp": 184,
		"keeper_adv_Att": 477,
		"keeper_adv_Cmp%": 38.6,
		"keeper_adv_Att__1": 849,
		"keeper_adv_Thr": 203,
		"keeper_adv_Launch%": 38.8,
		"keeper_adv_AvgLen": 37.1,
		"keeper_adv_Att__2": 294,
		"keeper_adv_Launch%__1": 50.3,
		"keeper_adv_AvgLen__1": 41.3,
		"keeper_adv_Opp": 397,
		"keeper_adv_Stp": 42,
		"keeper_adv_Stp%": 10.6,
		"keeper_adv_#OPA": 25,
		"keeper_adv_#OPA/90": 0.71,
		"keeper_adv_AvgDist": 13.8,
		"keeper_adv_Matches": "Matches"
	},
	"23": {
		"keeper_Player": "Andriy Lunin\\3061e1ec",
		"keeper_Nation": "ua UKR",
		"keeper_Pos": "GK",
		"keeper_Squad": "Real Madrid",
		"keeper_Age": 22,
		"keeper_Born": 1999,
		"keeper_MP": 2,
		"keeper_Starts": 2,
		"keeper_Min": 180,
		"keeper_90s": 2,
		"keeper_GA": 2,
		"keeper_GA90": 1,
		"keeper_SoTA": 7,
		"keeper_Saves": 6,
		"keeper_Save%": 85.7,
		"keeper_W": 0,
		"keeper_D": 1,
		"keeper_L": 1,
		"keeper_CS": 0,
		"keeper_CS%": 0,
		"keeper_PKatt": 2,
		"keeper_PKA": 1,
		"keeper_PKsv": 1,
		"keeper_PKm": 0,
		"keeper_Save%__1": 50,
		"keeper_Matches": "Matches",
		"code": "3061e1ec",
		"url": "/en/players/3061e1ec/Andriy-Lunin",
		"keeper_adv_Player": "Andriy Lunin\\3061e1ec",
		"keeper_adv_Nation": "ua UKR",
		"keeper_adv_Pos": "GK",
		"keeper_adv_Squad": "Real Madrid",
		"keeper_adv_Age": 22,
		"keeper_adv_Born": 1999,
		"keeper_adv_90s": 2,
		"keeper_adv_GA": 2,
		"keeper_adv_PKA": 1,
		"keeper_adv_FK": 0,
		"keeper_adv_CK": 1,
		"keeper_adv_OG": 0,
		"keeper_adv_PSxG": 3.7,
		"keeper_adv_PSxG/SoT": 0.29,
		"keeper_adv_PSxG+/-": "+1.7",
		"keeper_adv_/90": "+0.86",
		"keeper_adv_Cmp": 9,
		"keeper_adv_Att": 16,
		"keeper_adv_Cmp%": 56.3,
		"keeper_adv_Att__1": 57,
		"keeper_adv_Thr": 13,
		"keeper_adv_Launch%": 12.3,
		"keeper_adv_AvgLen": 24,
		"keeper_adv_Att__2": 25,
		"keeper_adv_Launch%__1": 36,
		"keeper_adv_AvgLen__1": 30.4,
		"keeper_adv_Opp": 25,
		"keeper_adv_Stp": 1,
		"keeper_adv_Stp%": 4,
		"keeper_adv_#OPA": 0,
		"keeper_adv_#OPA/90": 0,
		"keeper_adv_AvgDist": 10.4,
		"keeper_adv_Matches": "Matches"
	},
	"24": {
		"keeper_Player": "Giorgi Mamardashvili\\d4b73232",
		"keeper_Nation": "ge GEO",
		"keeper_Pos": "GK",
		"keeper_Squad": "Valencia",
		"keeper_Age": 20,
		"keeper_Born": 2000,
		"keeper_MP": 18,
		"keeper_Starts": 18,
		"keeper_Min": 1620,
		"keeper_90s": 18,
		"keeper_GA": 20,
		"keeper_GA90": 1.11,
		"keeper_SoTA": 74,
		"keeper_Saves": 56,
		"keeper_Save%": 75.7,
		"keeper_W": 5,
		"keeper_D": 7,
		"keeper_L": 6,
		"keeper_CS": 8,
		"keeper_CS%": 44.4,
		"keeper_PKatt": 2,
		"keeper_PKA": 2,
		"keeper_PKsv": 0,
		"keeper_PKm": 0,
		"keeper_Save%__1": 0,
		"keeper_Matches": "Matches",
		"code": "d4b73232",
		"url": "/en/players/d4b73232/Giorgi-Mamardashvili",
		"keeper_adv_Player": "Giorgi Mamardashvili\\d4b73232",
		"keeper_adv_Nation": "ge GEO",
		"keeper_adv_Pos": "GK",
		"keeper_adv_Squad": "Valencia",
		"keeper_adv_Age": 20,
		"keeper_adv_Born": 2000,
		"keeper_adv_90s": 18,
		"keeper_adv_GA": 20,
		"keeper_adv_PKA": 2,
		"keeper_adv_FK": 0,
		"keeper_adv_CK": 2,
		"keeper_adv_OG": 0,
		"keeper_adv_PSxG": 18,
		"keeper_adv_PSxG/SoT": 0.22,
		"keeper_adv_PSxG+/-": -2,
		"keeper_adv_/90": -0.11,
		"keeper_adv_Cmp": 140,
		"keeper_adv_Att": 338,
		"keeper_adv_Cmp%": 41.4,
		"keeper_adv_Att__1": 348,
		"keeper_adv_Thr": 57,
		"keeper_adv_Launch%": 62.9,
		"keeper_adv_AvgLen": 46.8,
		"keeper_adv_Att__2": 147,
		"keeper_adv_Launch%__1": 81,
		"keeper_adv_AvgLen__1": 59,
		"keeper_adv_Opp": 170,
		"keeper_adv_Stp": 15,
		"keeper_adv_Stp%": 8.8,
		"keeper_adv_#OPA": 16,
		"keeper_adv_#OPA/90": 0.89,
		"keeper_adv_AvgDist": 14.6,
		"keeper_adv_Matches": "Matches"
	},
	"25": {
		"keeper_Player": "Luís Maximiano\\3318286e",
		"keeper_Nation": "pt POR",
		"keeper_Pos": "GK",
		"keeper_Squad": "Granada",
		"keeper_Age": 22,
		"keeper_Born": 1999,
		"keeper_MP": 34,
		"keeper_Starts": 34,
		"keeper_Min": 3046,
		"keeper_90s": 33.8,
		"keeper_GA": 54,
		"keeper_GA90": 1.6,
		"keeper_SoTA": 170,
		"keeper_Saves": 121,
		"keeper_Save%": 71.2,
		"keeper_W": 8,
		"keeper_D": 12,
		"keeper_L": 14,
		"keeper_CS": 7,
		"keeper_CS%": 20.6,
		"keeper_PKatt": 7,
		"keeper_PKA": 5,
		"keeper_PKsv": 2,
		"keeper_PKm": 0,
		"keeper_Save%__1": 28.6,
		"keeper_Matches": "Matches",
		"code": "3318286e",
		"url": "/en/players/3318286e/Luis-Maximiano",
		"keeper_adv_Player": "Luís Maximiano\\3318286e",
		"keeper_adv_Nation": "pt POR",
		"keeper_adv_Pos": "GK",
		"keeper_adv_Squad": "Granada",
		"keeper_adv_Age": 22,
		"keeper_adv_Born": 1999,
		"keeper_adv_90s": 33.8,
		"keeper_adv_GA": 54,
		"keeper_adv_PKA": 5,
		"keeper_adv_FK": 0,
		"keeper_adv_CK": 8,
		"keeper_adv_OG": 2,
		"keeper_adv_PSxG": 58.3,
		"keeper_adv_PSxG/SoT": 0.31,
		"keeper_adv_PSxG+/-": "+5.3",
		"keeper_adv_/90": "+0.15",
		"keeper_adv_Cmp": 265,
		"keeper_adv_Att": 775,
		"keeper_adv_Cmp%": 34.2,
		"keeper_adv_Att__1": 837,
		"keeper_adv_Thr": 145,
		"keeper_adv_Launch%": 61.6,
		"keeper_adv_AvgLen": 47.2,
		"keeper_adv_Att__2": 336,
		"keeper_adv_Launch%__1": 77.1,
		"keeper_adv_AvgLen__1": 55.7,
		"keeper_adv_Opp": 375,
		"keeper_adv_Stp": 26,
		"keeper_adv_Stp%": 6.9,
		"keeper_adv_#OPA": 41,
		"keeper_adv_#OPA/90": 1.18,
		"keeper_adv_AvgDist": 15.9,
		"keeper_adv_Matches": "Matches"
	},
	"26": {
		"keeper_Player": "Neto\\a9dc785c",
		"keeper_Nation": "br BRA",
		"keeper_Pos": "GK",
		"keeper_Squad": "Barcelona",
		"keeper_Age": 32,
		"keeper_Born": 1989,
		"keeper_MP": 3,
		"keeper_Starts": 3,
		"keeper_Min": 270,
		"keeper_90s": 3,
		"keeper_GA": 4,
		"keeper_GA90": 1.33,
		"keeper_SoTA": 14,
		"keeper_Saves": 10,
		"keeper_Save%": 71.4,
		"keeper_W": 2,
		"keeper_D": 1,
		"keeper_L": 0,
		"keeper_CS": 0,
		"keeper_CS%": 0,
		"keeper_PKatt": 0,
		"keeper_PKA": 0,
		"keeper_PKsv": 0,
		"keeper_PKm": 0,
		"keeper_Save%__1": "",
		"keeper_Matches": "Matches",
		"code": "a9dc785c",
		"url": "/en/players/a9dc785c/Neto",
		"keeper_adv_Player": "Neto\\a9dc785c",
		"keeper_adv_Nation": "br BRA",
		"keeper_adv_Pos": "GK",
		"keeper_adv_Squad": "Barcelona",
		"keeper_adv_Age": 32,
		"keeper_adv_Born": 1989,
		"keeper_adv_90s": 3,
		"keeper_adv_GA": 4,
		"keeper_adv_PKA": 0,
		"keeper_adv_FK": 1,
		"keeper_adv_CK": 1,
		"keeper_adv_OG": 0,
		"keeper_adv_PSxG": 4,
		"keeper_adv_PSxG/SoT": 0.29,
		"keeper_adv_PSxG+/-": 0,
		"keeper_adv_/90": "+0.01",
		"keeper_adv_Cmp": 26,
		"keeper_adv_Att": 48,
		"keeper_adv_Cmp%": 54.2,
		"keeper_adv_Att__1": 108,
		"keeper_adv_Thr": 18,
		"keeper_adv_Launch%": 41.7,
		"keeper_adv_AvgLen": 36.1,
		"keeper_adv_Att__2": 22,
		"keeper_adv_Launch%__1": 13.6,
		"keeper_adv_AvgLen__1": 28.2,
		"keeper_adv_Opp": 25,
		"keeper_adv_Stp": 1,
		"keeper_adv_Stp%": 4,
		"keeper_adv_#OPA": 2,
		"keeper_adv_#OPA/90": 0.67,
		"keeper_adv_AvgDist": 14.3,
		"keeper_adv_Matches": "Matches"
	},
	"27": {
		"keeper_Player": "Jan Oblak\\ee8508c0",
		"keeper_Nation": "si SVN",
		"keeper_Pos": "GK",
		"keeper_Squad": "Atlético Madrid",
		"keeper_Age": 28,
		"keeper_Born": 1993,
		"keeper_MP": 38,
		"keeper_Starts": 38,
		"keeper_Min": 3420,
		"keeper_90s": 38,
		"keeper_GA": 43,
		"keeper_GA90": 1.13,
		"keeper_SoTA": 96,
		"keeper_Saves": 62,
		"keeper_Save%": 62.5,
		"keeper_W": 21,
		"keeper_D": 8,
		"keeper_L": 9,
		"keeper_CS": 12,
		"keeper_CS%": 31.6,
		"keeper_PKatt": 8,
		"keeper_PKA": 7,
		"keeper_PKsv": 1,
		"keeper_PKm": 0,
		"keeper_Save%__1": 12.5,
		"keeper_Matches": "Matches",
		"code": "ee8508c0",
		"url": "/en/players/ee8508c0/Jan-Oblak",
		"keeper_adv_Player": "Jan Oblak\\ee8508c0",
		"keeper_adv_Nation": "si SVN",
		"keeper_adv_Pos": "GK",
		"keeper_adv_Squad": "Atlético Madrid",
		"keeper_adv_Age": 28,
		"keeper_adv_Born": 1993,
		"keeper_adv_90s": 38,
		"keeper_adv_GA": 43,
		"keeper_adv_PKA": 7,
		"keeper_adv_FK": 2,
		"keeper_adv_CK": 4,
		"keeper_adv_OG": 3,
		"keeper_adv_PSxG": 33.9,
		"keeper_adv_PSxG/SoT": 0.28,
		"keeper_adv_PSxG+/-": -6.1,
		"keeper_adv_/90": -0.16,
		"keeper_adv_Cmp": 203,
		"keeper_adv_Att": 647,
		"keeper_adv_Cmp%": 31.4,
		"keeper_adv_Att__1": 812,
		"keeper_adv_Thr": 149,
		"keeper_adv_Launch%": 55.9,
		"keeper_adv_AvgLen": 44.1,
		"keeper_adv_Att__2": 283,
		"keeper_adv_Launch%__1": 68.2,
		"keeper_adv_AvgLen__1": 51.5,
		"keeper_adv_Opp": 292,
		"keeper_adv_Stp": 20,
		"keeper_adv_Stp%": 6.8,
		"keeper_adv_#OPA": 16,
		"keeper_adv_#OPA/90": 0.42,
		"keeper_adv_AvgDist": 13.9,
		"keeper_adv_Matches": "Matches"
	},
	"28": {
		"keeper_Player": "Oier Olazábal\\b5bdf144",
		"keeper_Nation": "es ESP",
		"keeper_Pos": "GK",
		"keeper_Squad": "Espanyol",
		"keeper_Age": 31,
		"keeper_Born": 1989,
		"keeper_MP": 2,
		"keeper_Starts": 1,
		"keeper_Min": 135,
		"keeper_90s": 1.5,
		"keeper_GA": 1,
		"keeper_GA90": 0.67,
		"keeper_SoTA": 7,
		"keeper_Saves": 7,
		"keeper_Save%": 100,
		"keeper_W": 0,
		"keeper_D": 0,
		"keeper_L": 1,
		"keeper_CS": 1,
		"keeper_CS%": 100,
		"keeper_PKatt": 1,
		"keeper_PKA": 1,
		"keeper_PKsv": 0,
		"keeper_PKm": 0,
		"keeper_Save%__1": 0,
		"keeper_Matches": "Matches",
		"code": "b5bdf144",
		"url": "/en/players/b5bdf144/Oier-Olazabal",
		"keeper_adv_Player": "Oier Olazábal\\b5bdf144",
		"keeper_adv_Nation": "es ESP",
		"keeper_adv_Pos": "GK",
		"keeper_adv_Squad": "Espanyol",
		"keeper_adv_Age": 31,
		"keeper_adv_Born": 1989,
		"keeper_adv_90s": 1.5,
		"keeper_adv_GA": 1,
		"keeper_adv_PKA": 1,
		"keeper_adv_FK": 0,
		"keeper_adv_CK": 0,
		"keeper_adv_OG": 0,
		"keeper_adv_PSxG": 2.9,
		"keeper_adv_PSxG/SoT": 0.28,
		"keeper_adv_PSxG+/-": "+1.9",
		"keeper_adv_/90": "+1.26",
		"keeper_adv_Cmp": 10,
		"keeper_adv_Att": 29,
		"keeper_adv_Cmp%": 34.5,
		"keeper_adv_Att__1": 33,
		"keeper_adv_Thr": 5,
		"keeper_adv_Launch%": 57.6,
		"keeper_adv_AvgLen": 42.5,
		"keeper_adv_Att__2": 10,
		"keeper_adv_Launch%__1": 100,
		"keeper_adv_AvgLen__1": 60.4,
		"keeper_adv_Opp": 19,
		"keeper_adv_Stp": 0,
		"keeper_adv_Stp%": 0,
		"keeper_adv_#OPA": 0,
		"keeper_adv_#OPA/90": 0,
		"keeper_adv_AvgDist": 9,
		"keeper_adv_Matches": "Matches"
	},
	"29": {
		"keeper_Player": "Jesús Owono\\d6e3d7fb",
		"keeper_Nation": "gq EQG",
		"keeper_Pos": "GK",
		"keeper_Squad": "Alavés",
		"keeper_Age": 20,
		"keeper_Born": 2001,
		"keeper_MP": 1,
		"keeper_Starts": 1,
		"keeper_Min": 90,
		"keeper_90s": 1,
		"keeper_GA": 1,
		"keeper_GA90": 1,
		"keeper_SoTA": 4,
		"keeper_Saves": 3,
		"keeper_Save%": 75,
		"keeper_W": 0,
		"keeper_D": 1,
		"keeper_L": 0,
		"keeper_CS": 0,
		"keeper_CS%": 0,
		"keeper_PKatt": 0,
		"keeper_PKA": 0,
		"keeper_PKsv": 0,
		"keeper_PKm": 0,
		"keeper_Save%__1": "",
		"keeper_Matches": "Matches",
		"code": "d6e3d7fb",
		"url": "/en/players/d6e3d7fb/Jesus-Owono",
		"keeper_adv_Player": "Jesús Owono\\d6e3d7fb",
		"keeper_adv_Nation": "gq EQG",
		"keeper_adv_Pos": "GK",
		"keeper_adv_Squad": "Alavés",
		"keeper_adv_Age": 20,
		"keeper_adv_Born": 2001,
		"keeper_adv_90s": 1,
		"keeper_adv_GA": 1,
		"keeper_adv_PKA": 0,
		"keeper_adv_FK": 0,
		"keeper_adv_CK": 0,
		"keeper_adv_OG": 0,
		"keeper_adv_PSxG": 0.7,
		"keeper_adv_PSxG/SoT": 0.16,
		"keeper_adv_PSxG+/-": -0.3,
		"keeper_adv_/90": -0.35,
		"keeper_adv_Cmp": 9,
		"keeper_adv_Att": 21,
		"keeper_adv_Cmp%": 42.9,
		"keeper_adv_Att__1": 20,
		"keeper_adv_Thr": 2,
		"keeper_adv_Launch%": 90,
		"keeper_adv_AvgLen": 60,
		"keeper_adv_Att__2": 3,
		"keeper_adv_Launch%__1": 100,
		"keeper_adv_AvgLen__1": 75,
		"keeper_adv_Opp": 4,
		"keeper_adv_Stp": 0,
		"keeper_adv_Stp%": 0,
		"keeper_adv_#OPA": 2,
		"keeper_adv_#OPA/90": 2,
		"keeper_adv_AvgDist": 15.7,
		"keeper_adv_Matches": "Matches"
	},
	"30": {
		"keeper_Player": "Fernando Pacheco\\97852360",
		"keeper_Nation": "es ESP",
		"keeper_Pos": "GK",
		"keeper_Squad": "Alavés",
		"keeper_Age": 29,
		"keeper_Born": 1992,
		"keeper_MP": 34,
		"keeper_Starts": 34,
		"keeper_Min": 3053,
		"keeper_90s": 33.9,
		"keeper_GA": 60,
		"keeper_GA90": 1.77,
		"keeper_SoTA": 139,
		"keeper_Saves": 83,
		"keeper_Save%": 60.4,
		"keeper_W": 8,
		"keeper_D": 5,
		"keeper_L": 21,
		"keeper_CS": 6,
		"keeper_CS%": 17.6,
		"keeper_PKatt": 8,
		"keeper_PKA": 5,
		"keeper_PKsv": 3,
		"keeper_PKm": 0,
		"keeper_Save%__1": 37.5,
		"keeper_Matches": "Matches",
		"code": "97852360",
		"url": "/en/players/97852360/Fernando-Pacheco",
		"keeper_adv_Player": "Fernando Pacheco\\97852360",
		"keeper_adv_Nation": "es ESP",
		"keeper_adv_Pos": "GK",
		"keeper_adv_Squad": "Alavés",
		"keeper_adv_Age": 29,
		"keeper_adv_Born": 1992,
		"keeper_adv_90s": 33.9,
		"keeper_adv_GA": 60,
		"keeper_adv_PKA": 5,
		"keeper_adv_FK": 0,
		"keeper_adv_CK": 10,
		"keeper_adv_OG": 0,
		"keeper_adv_PSxG": 54.3,
		"keeper_adv_PSxG/SoT": 0.35,
		"keeper_adv_PSxG+/-": -5.7,
		"keeper_adv_/90": -0.17,
		"keeper_adv_Cmp": 367,
		"keeper_adv_Att": 742,
		"keeper_adv_Cmp%": 49.5,
		"keeper_adv_Att__1": 718,
		"keeper_adv_Thr": 81,
		"keeper_adv_Launch%": 70.6,
		"keeper_adv_AvgLen": 50.4,
		"keeper_adv_Att__2": 308,
		"keeper_adv_Launch%__1": 76.3,
		"keeper_adv_AvgLen__1": 53.3,
		"keeper_adv_Opp": 337,
		"keeper_adv_Stp": 28,
		"keeper_adv_Stp%": 8.3,
		"keeper_adv_#OPA": 24,
		"keeper_adv_#OPA/90": 0.71,
		"keeper_adv_AvgDist": 14.6,
		"keeper_adv_Matches": "Matches"
	},
	"31": {
		"keeper_Player": "Juan Pérez\\8f29e08b",
		"keeper_Nation": "es ESP",
		"keeper_Pos": "GK",
		"keeper_Squad": "Osasuna",
		"keeper_Age": 25,
		"keeper_Born": 1996,
		"keeper_MP": 2,
		"keeper_Starts": 2,
		"keeper_Min": 180,
		"keeper_90s": 2,
		"keeper_GA": 3,
		"keeper_GA90": 1.5,
		"keeper_SoTA": 4,
		"keeper_Saves": 2,
		"keeper_Save%": 25,
		"keeper_W": 0,
		"keeper_D": 1,
		"keeper_L": 1,
		"keeper_CS": 0,
		"keeper_CS%": 0,
		"keeper_PKatt": 0,
		"keeper_PKA": 0,
		"keeper_PKsv": 0,
		"keeper_PKm": 0,
		"keeper_Save%__1": "",
		"keeper_Matches": "Matches",
		"code": "8f29e08b",
		"url": "/en/players/8f29e08b/Juan-Perez",
		"keeper_adv_Player": "Juan Pérez\\8f29e08b",
		"keeper_adv_Nation": "es ESP",
		"keeper_adv_Pos": "GK",
		"keeper_adv_Squad": "Osasuna",
		"keeper_adv_Age": 25,
		"keeper_adv_Born": 1996,
		"keeper_adv_90s": 2,
		"keeper_adv_GA": 3,
		"keeper_adv_PKA": 0,
		"keeper_adv_FK": 0,
		"keeper_adv_CK": 1,
		"keeper_adv_OG": 1,
		"keeper_adv_PSxG": 0.9,
		"keeper_adv_PSxG/SoT": 0.23,
		"keeper_adv_PSxG+/-": -1.1,
		"keeper_adv_/90": -0.54,
		"keeper_adv_Cmp": 8,
		"keeper_adv_Att": 31,
		"keeper_adv_Cmp%": 25.8,
		"keeper_adv_Att__1": 33,
		"keeper_adv_Thr": 6,
		"keeper_adv_Launch%": 69.7,
		"keeper_adv_AvgLen": 49.6,
		"keeper_adv_Att__2": 9,
		"keeper_adv_Launch%__1": 88.9,
		"keeper_adv_AvgLen__1": 65.2,
		"keeper_adv_Opp": 12,
		"keeper_adv_Stp": 1,
		"keeper_adv_Stp%": 8.3,
		"keeper_adv_#OPA": 3,
		"keeper_adv_#OPA/90": 1.5,
		"keeper_adv_AvgDist": 17.2,
		"keeper_adv_Matches": "Matches"
	},
	"32": {
		"keeper_Player": "Alejandro Primo\\f38284bb",
		"keeper_Nation": "es ESP",
		"keeper_Pos": "GK",
		"keeper_Squad": "Levante",
		"keeper_Age": 17,
		"keeper_Born": 2004,
		"keeper_MP": 1,
		"keeper_Starts": 1,
		"keeper_Min": 90,
		"keeper_90s": 1,
		"keeper_GA": 1,
		"keeper_GA90": 1,
		"keeper_SoTA": 2,
		"keeper_Saves": 1,
		"keeper_Save%": 50,
		"keeper_W": 1,
		"keeper_D": 0,
		"keeper_L": 0,
		"keeper_CS": 0,
		"keeper_CS%": 0,
		"keeper_PKatt": 0,
		"keeper_PKA": 0,
		"keeper_PKsv": 0,
		"keeper_PKm": 0,
		"keeper_Save%__1": "",
		"keeper_Matches": "Matches",
		"code": "f38284bb",
		"url": "/en/players/f38284bb/Alejandro-Primo",
		"keeper_adv_Player": "Alejandro Primo\\f38284bb",
		"keeper_adv_Nation": "es ESP",
		"keeper_adv_Pos": "GK",
		"keeper_adv_Squad": "Levante",
		"keeper_adv_Age": 17,
		"keeper_adv_Born": 2004,
		"keeper_adv_90s": 1,
		"keeper_adv_GA": 1,
		"keeper_adv_PKA": 0,
		"keeper_adv_FK": 0,
		"keeper_adv_CK": 0,
		"keeper_adv_OG": 0,
		"keeper_adv_PSxG": 0.4,
		"keeper_adv_PSxG/SoT": 0.19,
		"keeper_adv_PSxG+/-": -0.6,
		"keeper_adv_/90": -0.62,
		"keeper_adv_Cmp": 4,
		"keeper_adv_Att": 9,
		"keeper_adv_Cmp%": 44.4,
		"keeper_adv_Att__1": 18,
		"keeper_adv_Thr": 0,
		"keeper_adv_Launch%": 38.9,
		"keeper_adv_AvgLen": 32.9,
		"keeper_adv_Att__2": 8,
		"keeper_adv_Launch%__1": 25,
		"keeper_adv_AvgLen__1": 23.1,
		"keeper_adv_Opp": 10,
		"keeper_adv_Stp": 0,
		"keeper_adv_Stp%": 0,
		"keeper_adv_#OPA": 0,
		"keeper_adv_#OPA/90": 0,
		"keeper_adv_AvgDist": 9,
		"keeper_adv_Matches": "Matches"
	},
	"33": {
		"keeper_Player": "Manolo Reina\\605eb473",
		"keeper_Nation": "es ESP",
		"keeper_Pos": "GK",
		"keeper_Squad": "Mallorca",
		"keeper_Age": 36,
		"keeper_Born": 1985,
		"keeper_MP": 21,
		"keeper_Starts": 21,
		"keeper_Min": 1890,
		"keeper_90s": 21,
		"keeper_GA": 26,
		"keeper_GA90": 1.24,
		"keeper_SoTA": 72,
		"keeper_Saves": 47,
		"keeper_Save%": 66.7,
		"keeper_W": 6,
		"keeper_D": 9,
		"keeper_L": 6,
		"keeper_CS": 8,
		"keeper_CS%": 38.1,
		"keeper_PKatt": 3,
		"keeper_PKA": 2,
		"keeper_PKsv": 1,
		"keeper_PKm": 0,
		"keeper_Save%__1": 33.3,
		"keeper_Matches": "Matches",
		"code": "605eb473",
		"url": "/en/players/605eb473/Manolo-Reina",
		"keeper_adv_Player": "Manolo Reina\\605eb473",
		"keeper_adv_Nation": "es ESP",
		"keeper_adv_Pos": "GK",
		"keeper_adv_Squad": "Mallorca",
		"keeper_adv_Age": 36,
		"keeper_adv_Born": 1985,
		"keeper_adv_90s": 21,
		"keeper_adv_GA": 26,
		"keeper_adv_PKA": 2,
		"keeper_adv_FK": 0,
		"keeper_adv_CK": 2,
		"keeper_adv_OG": 1,
		"keeper_adv_PSxG": 24.6,
		"keeper_adv_PSxG/SoT": 0.3,
		"keeper_adv_PSxG+/-": -0.4,
		"keeper_adv_/90": -0.02,
		"keeper_adv_Cmp": 145,
		"keeper_adv_Att": 381,
		"keeper_adv_Cmp%": 38.1,
		"keeper_adv_Att__1": 457,
		"keeper_adv_Thr": 69,
		"keeper_adv_Launch%": 58.2,
		"keeper_adv_AvgLen": 46.1,
		"keeper_adv_Att__2": 183,
		"keeper_adv_Launch%__1": 62.8,
		"keeper_adv_AvgLen__1": 47.7,
		"keeper_adv_Opp": 219,
		"keeper_adv_Stp": 15,
		"keeper_adv_Stp%": 6.8,
		"keeper_adv_#OPA": 11,
		"keeper_adv_#OPA/90": 0.52,
		"keeper_adv_AvgDist": 14.4,
		"keeper_adv_Matches": "Matches"
	},
	"34": {
		"keeper_Player": "Álex Remiro\\374ee424",
		"keeper_Nation": "es ESP",
		"keeper_Pos": "GK",
		"keeper_Squad": "Real Sociedad",
		"keeper_Age": 26,
		"keeper_Born": 1995,
		"keeper_MP": 35,
		"keeper_Starts": 35,
		"keeper_Min": 3150,
		"keeper_90s": 35,
		"keeper_GA": 32,
		"keeper_GA90": 0.91,
		"keeper_SoTA": 107,
		"keeper_Saves": 77,
		"keeper_Save%": 73.8,
		"keeper_W": 15,
		"keeper_D": 11,
		"keeper_L": 9,
		"keeper_CS": 19,
		"keeper_CS%": 54.3,
		"keeper_PKatt": 5,
		"keeper_PKA": 4,
		"keeper_PKsv": 1,
		"keeper_PKm": 0,
		"keeper_Save%__1": 20,
		"keeper_Matches": "Matches",
		"code": "374ee424",
		"url": "/en/players/374ee424/Alex-Remiro",
		"keeper_adv_Player": "Álex Remiro\\374ee424",
		"keeper_adv_Nation": "es ESP",
		"keeper_adv_Pos": "GK",
		"keeper_adv_Squad": "Real Sociedad",
		"keeper_adv_Age": 26,
		"keeper_adv_Born": 1995,
		"keeper_adv_90s": 35,
		"keeper_adv_GA": 32,
		"keeper_adv_PKA": 4,
		"keeper_adv_FK": 1,
		"keeper_adv_CK": 5,
		"keeper_adv_OG": 0,
		"keeper_adv_PSxG": 34.6,
		"keeper_adv_PSxG/SoT": 0.28,
		"keeper_adv_PSxG+/-": "+2.6",
		"keeper_adv_/90": "+0.08",
		"keeper_adv_Cmp": 261,
		"keeper_adv_Att": 547,
		"keeper_adv_Cmp%": 47.7,
		"keeper_adv_Att__1": 1009,
		"keeper_adv_Thr": 118,
		"keeper_adv_Launch%": 40.2,
		"keeper_adv_AvgLen": 36.3,
		"keeper_adv_Att__2": 242,
		"keeper_adv_Launch%__1": 58.3,
		"keeper_adv_AvgLen__1": 47.8,
		"keeper_adv_Opp": 305,
		"keeper_adv_Stp": 22,
		"keeper_adv_Stp%": 7.2,
		"keeper_adv_#OPA": 37,
		"keeper_adv_#OPA/90": 1.06,
		"keeper_adv_AvgDist": 15.8,
		"keeper_adv_Matches": "Matches"
	},
	"35": {
		"keeper_Player": "Sergio Rico\\5f0241b2",
		"keeper_Nation": "es ESP",
		"keeper_Pos": "GK",
		"keeper_Squad": "Mallorca",
		"keeper_Age": 27,
		"keeper_Born": 1993,
		"keeper_MP": 14,
		"keeper_Starts": 14,
		"keeper_Min": 1260,
		"keeper_90s": 14,
		"keeper_GA": 29,
		"keeper_GA90": 2.07,
		"keeper_SoTA": 52,
		"keeper_Saves": 28,
		"keeper_Save%": 50,
		"keeper_W": 4,
		"keeper_D": 0,
		"keeper_L": 10,
		"keeper_CS": 1,
		"keeper_CS%": 7.1,
		"keeper_PKatt": 4,
		"keeper_PKA": 3,
		"keeper_PKsv": 1,
		"keeper_PKm": 0,
		"keeper_Save%__1": 25,
		"keeper_Matches": "Matches",
		"code": "5f0241b2",
		"url": "/en/players/5f0241b2/Sergio-Rico",
		"keeper_adv_Player": "Sergio Rico\\5f0241b2",
		"keeper_adv_Nation": "es ESP",
		"keeper_adv_Pos": "GK",
		"keeper_adv_Squad": "Mallorca",
		"keeper_adv_Age": 27,
		"keeper_adv_Born": 1993,
		"keeper_adv_90s": 14,
		"keeper_adv_GA": 29,
		"keeper_adv_PKA": 3,
		"keeper_adv_FK": 0,
		"keeper_adv_CK": 4,
		"keeper_adv_OG": 2,
		"keeper_adv_PSxG": 22.4,
		"keeper_adv_PSxG/SoT": 0.37,
		"keeper_adv_PSxG+/-": -4.6,
		"keeper_adv_/90": -0.33,
		"keeper_adv_Cmp": 104,
		"keeper_adv_Att": 213,
		"keeper_adv_Cmp%": 48.8,
		"keeper_adv_Att__1": 268,
		"keeper_adv_Thr": 46,
		"keeper_adv_Launch%": 56.3,
		"keeper_adv_AvgLen": 44.6,
		"keeper_adv_Att__2": 91,
		"keeper_adv_Launch%__1": 68.1,
		"keeper_adv_AvgLen__1": 51.4,
		"keeper_adv_Opp": 127,
		"keeper_adv_Stp": 6,
		"keeper_adv_Stp%": 4.7,
		"keeper_adv_#OPA": 4,
		"keeper_adv_#OPA/90": 0.29,
		"keeper_adv_AvgDist": 12.2,
		"keeper_adv_Matches": "Matches"
	},
	"36": {
		"keeper_Player": "Leonardo Román\\924ff27e",
		"keeper_Nation": "es ESP",
		"keeper_Pos": "GK",
		"keeper_Squad": "Mallorca",
		"keeper_Age": 21,
		"keeper_Born": 2000,
		"keeper_MP": 2,
		"keeper_Starts": 2,
		"keeper_Min": 180,
		"keeper_90s": 2,
		"keeper_GA": 5,
		"keeper_GA90": 2.5,
		"keeper_SoTA": 13,
		"keeper_Saves": 10,
		"keeper_Save%": 69.2,
		"keeper_W": 0,
		"keeper_D": 0,
		"keeper_L": 2,
		"keeper_CS": 0,
		"keeper_CS%": 0,
		"keeper_PKatt": 1,
		"keeper_PKA": 1,
		"keeper_PKsv": 0,
		"keeper_PKm": 0,
		"keeper_Save%__1": 0,
		"keeper_Matches": "Matches",
		"code": "924ff27e",
		"url": "/en/players/924ff27e/Leonardo-Roman",
		"keeper_adv_Player": "Leonardo Román\\924ff27e",
		"keeper_adv_Nation": "es ESP",
		"keeper_adv_Pos": "GK",
		"keeper_adv_Squad": "Mallorca",
		"keeper_adv_Age": 21,
		"keeper_adv_Born": 2000,
		"keeper_adv_90s": 2,
		"keeper_adv_GA": 5,
		"keeper_adv_PKA": 1,
		"keeper_adv_FK": 0,
		"keeper_adv_CK": 0,
		"keeper_adv_OG": 1,
		"keeper_adv_PSxG": 3.1,
		"keeper_adv_PSxG/SoT": 0.19,
		"keeper_adv_PSxG+/-": -0.9,
		"keeper_adv_/90": -0.43,
		"keeper_adv_Cmp": 12,
		"keeper_adv_Att": 32,
		"keeper_adv_Cmp%": 37.5,
		"keeper_adv_Att__1": 53,
		"keeper_adv_Thr": 6,
		"keeper_adv_Launch%": 47.2,
		"keeper_adv_AvgLen": 39.7,
		"keeper_adv_Att__2": 16,
		"keeper_adv_Launch%__1": 43.8,
		"keeper_adv_AvgLen__1": 38.7,
		"keeper_adv_Opp": 21,
		"keeper_adv_Stp": 2,
		"keeper_adv_Stp%": 9.5,
		"keeper_adv_#OPA": 3,
		"keeper_adv_#OPA/90": 1.5,
		"keeper_adv_AvgDist": 17,
		"keeper_adv_Matches": "Matches"
	},
	"37": {
		"keeper_Player": "Gerónimo Rulli\\625c144a",
		"keeper_Nation": "ar ARG",
		"keeper_Pos": "GK",
		"keeper_Squad": "Villarreal",
		"keeper_Age": 29,
		"keeper_Born": 1992,
		"keeper_MP": 32,
		"keeper_Starts": 32,
		"keeper_Min": 2880,
		"keeper_90s": 32,
		"keeper_GA": 28,
		"keeper_GA90": 0.87,
		"keeper_SoTA": 97,
		"keeper_Saves": 70,
		"keeper_Save%": 74.2,
		"keeper_W": 14,
		"keeper_D": 9,
		"keeper_L": 9,
		"keeper_CS": 14,
		"keeper_CS%": 43.8,
		"keeper_PKatt": 4,
		"keeper_PKA": 3,
		"keeper_PKsv": 1,
		"keeper_PKm": 0,
		"keeper_Save%__1": 25,
		"keeper_Matches": "Matches",
		"code": "625c144a",
		"url": "/en/players/625c144a/Geronimo-Rulli",
		"keeper_adv_Player": "Gerónimo Rulli\\625c144a",
		"keeper_adv_Nation": "ar ARG",
		"keeper_adv_Pos": "GK",
		"keeper_adv_Squad": "Villarreal",
		"keeper_adv_Age": 29,
		"keeper_adv_Born": 1992,
		"keeper_adv_90s": 32,
		"keeper_adv_GA": 28,
		"keeper_adv_PKA": 3,
		"keeper_adv_FK": 0,
		"keeper_adv_CK": 3,
		"keeper_adv_OG": 1,
		"keeper_adv_PSxG": 28.4,
		"keeper_adv_PSxG/SoT": 0.27,
		"keeper_adv_PSxG+/-": "+1.4",
		"keeper_adv_/90": "+0.04",
		"keeper_adv_Cmp": 170,
		"keeper_adv_Att": 389,
		"keeper_adv_Cmp%": 43.7,
		"keeper_adv_Att__1": 1072,
		"keeper_adv_Thr": 161,
		"keeper_adv_Launch%": 27.7,
		"keeper_adv_AvgLen": 33.8,
		"keeper_adv_Att__2": 209,
		"keeper_adv_Launch%__1": 44,
		"keeper_adv_AvgLen__1": 40.5,
		"keeper_adv_Opp": 306,
		"keeper_adv_Stp": 27,
		"keeper_adv_Stp%": 8.8,
		"keeper_adv_#OPA": 31,
		"keeper_adv_#OPA/90": 0.97,
		"keeper_adv_AvgDist": 15.5,
		"keeper_adv_Matches": "Matches"
	},
	"38": {
		"keeper_Player": "Mathew Ryan\\4535e4bb",
		"keeper_Nation": "au AUS",
		"keeper_Pos": "GK",
		"keeper_Squad": "Real Sociedad",
		"keeper_Age": 29,
		"keeper_Born": 1992,
		"keeper_MP": 3,
		"keeper_Starts": 3,
		"keeper_Min": 270,
		"keeper_90s": 3,
		"keeper_GA": 5,
		"keeper_GA90": 1.67,
		"keeper_SoTA": 15,
		"keeper_Saves": 11,
		"keeper_Save%": 73.3,
		"keeper_W": 2,
		"keeper_D": 0,
		"keeper_L": 1,
		"keeper_CS": 1,
		"keeper_CS%": 33.3,
		"keeper_PKatt": 1,
		"keeper_PKA": 1,
		"keeper_PKsv": 0,
		"keeper_PKm": 0,
		"keeper_Save%__1": 0,
		"keeper_Matches": "Matches",
		"code": "4535e4bb",
		"url": "/en/players/4535e4bb/Mathew-Ryan",
		"keeper_adv_Player": "Mathew Ryan\\4535e4bb",
		"keeper_adv_Nation": "au AUS",
		"keeper_adv_Pos": "GK",
		"keeper_adv_Squad": "Real Sociedad",
		"keeper_adv_Age": 29,
		"keeper_adv_Born": 1992,
		"keeper_adv_90s": 3,
		"keeper_adv_GA": 5,
		"keeper_adv_PKA": 1,
		"keeper_adv_FK": 0,
		"keeper_adv_CK": 3,
		"keeper_adv_OG": 0,
		"keeper_adv_PSxG": 5,
		"keeper_adv_PSxG/SoT": 0.28,
		"keeper_adv_PSxG+/-": 0,
		"keeper_adv_/90": "+0.01",
		"keeper_adv_Cmp": 20,
		"keeper_adv_Att": 58,
		"keeper_adv_Cmp%": 34.5,
		"keeper_adv_Att__1": 88,
		"keeper_adv_Thr": 14,
		"keeper_adv_Launch%": 51.1,
		"keeper_adv_AvgLen": 42.2,
		"keeper_adv_Att__2": 19,
		"keeper_adv_Launch%__1": 68.4,
		"keeper_adv_AvgLen__1": 49.3,
		"keeper_adv_Opp": 36,
		"keeper_adv_Stp": 4,
		"keeper_adv_Stp%": 11.1,
		"keeper_adv_#OPA": 1,
		"keeper_adv_#OPA/90": 0.33,
		"keeper_adv_AvgDist": 14.2,
		"keeper_adv_Matches": "Matches"
	},
	"39": {
		"keeper_Player": "Rui Silva\\ea83bfa6",
		"keeper_Nation": "pt POR",
		"keeper_Pos": "GK",
		"keeper_Squad": "Betis",
		"keeper_Age": 27,
		"keeper_Born": 1994,
		"keeper_MP": 22,
		"keeper_Starts": 21,
		"keeper_Min": 1964,
		"keeper_90s": 21.8,
		"keeper_GA": 21,
		"keeper_GA90": 0.96,
		"keeper_SoTA": 72,
		"keeper_Saves": 52,
		"keeper_Save%": 73.6,
		"keeper_W": 11,
		"keeper_D": 4,
		"keeper_L": 6,
		"keeper_CS": 8,
		"keeper_CS%": 38.1,
		"keeper_PKatt": 2,
		"keeper_PKA": 2,
		"keeper_PKsv": 0,
		"keeper_PKm": 0,
		"keeper_Save%__1": 0,
		"keeper_Matches": "Matches",
		"code": "ea83bfa6",
		"url": "/en/players/ea83bfa6/Rui-Silva",
		"keeper_adv_Player": "Rui Silva\\ea83bfa6",
		"keeper_adv_Nation": "pt POR",
		"keeper_adv_Pos": "GK",
		"keeper_adv_Squad": "Betis",
		"keeper_adv_Age": 27,
		"keeper_adv_Born": 1994,
		"keeper_adv_90s": 21.8,
		"keeper_adv_GA": 21,
		"keeper_adv_PKA": 2,
		"keeper_adv_FK": 0,
		"keeper_adv_CK": 3,
		"keeper_adv_OG": 0,
		"keeper_adv_PSxG": 22,
		"keeper_adv_PSxG/SoT": 0.28,
		"keeper_adv_PSxG+/-": "+1.0",
		"keeper_adv_/90": "+0.04",
		"keeper_adv_Cmp": 130,
		"keeper_adv_Att": 323,
		"keeper_adv_Cmp%": 40.2,
		"keeper_adv_Att__1": 548,
		"keeper_adv_Thr": 92,
		"keeper_adv_Launch%": 41.6,
		"keeper_adv_AvgLen": 37,
		"keeper_adv_Att__2": 176,
		"keeper_adv_Launch%__1": 54,
		"keeper_adv_AvgLen__1": 44.6,
		"keeper_adv_Opp": 207,
		"keeper_adv_Stp": 11,
		"keeper_adv_Stp%": 5.3,
		"keeper_adv_#OPA": 20,
		"keeper_adv_#OPA/90": 0.92,
		"keeper_adv_AvgDist": 14.1,
		"keeper_adv_Matches": "Matches"
	},
	"40": {
		"keeper_Player": "Unai Simón\\5dcf3e90",
		"keeper_Nation": "es ESP",
		"keeper_Pos": "GK",
		"keeper_Squad": "Athletic Club",
		"keeper_Age": 24,
		"keeper_Born": 1997,
		"keeper_MP": 34,
		"keeper_Starts": 34,
		"keeper_Min": 3060,
		"keeper_90s": 34,
		"keeper_GA": 31,
		"keeper_GA90": 0.91,
		"keeper_SoTA": 106,
		"keeper_Saves": 74,
		"keeper_Save%": 73.6,
		"keeper_W": 13,
		"keeper_D": 11,
		"keeper_L": 10,
		"keeper_CS": 12,
		"keeper_CS%": 35.3,
		"keeper_PKatt": 3,
		"keeper_PKA": 3,
		"keeper_PKsv": 0,
		"keeper_PKm": 0,
		"keeper_Save%__1": 0,
		"keeper_Matches": "Matches",
		"code": "5dcf3e90",
		"url": "/en/players/5dcf3e90/Unai-Simon",
		"keeper_adv_Player": "Unai Simón\\5dcf3e90",
		"keeper_adv_Nation": "es ESP",
		"keeper_adv_Pos": "GK",
		"keeper_adv_Squad": "Athletic Club",
		"keeper_adv_Age": 24,
		"keeper_adv_Born": 1997,
		"keeper_adv_90s": 34,
		"keeper_adv_GA": 31,
		"keeper_adv_PKA": 3,
		"keeper_adv_FK": 0,
		"keeper_adv_CK": 2,
		"keeper_adv_OG": 1,
		"keeper_adv_PSxG": 29.9,
		"keeper_adv_PSxG/SoT": 0.26,
		"keeper_adv_PSxG+/-": -0.1,
		"keeper_adv_/90": 0,
		"keeper_adv_Cmp": 179,
		"keeper_adv_Att": 416,
		"keeper_adv_Cmp%": 43,
		"keeper_adv_Att__1": 691,
		"keeper_adv_Thr": 181,
		"keeper_adv_Launch%": 42.3,
		"keeper_adv_AvgLen": 37.4,
		"keeper_adv_Att__2": 242,
		"keeper_adv_Launch%__1": 51.2,
		"keeper_adv_AvgLen__1": 44,
		"keeper_adv_Opp": 372,
		"keeper_adv_Stp": 23,
		"keeper_adv_Stp%": 6.2,
		"keeper_adv_#OPA": 23,
		"keeper_adv_#OPA/90": 0.68,
		"keeper_adv_AvgDist": 15.2,
		"keeper_adv_Matches": "Matches"
	},
	"41": {
		"keeper_Player": "Antonio Sivera\\9970da54",
		"keeper_Nation": "es ESP",
		"keeper_Pos": "GK",
		"keeper_Squad": "Alavés",
		"keeper_Age": 24,
		"keeper_Born": 1996,
		"keeper_MP": 4,
		"keeper_Starts": 3,
		"keeper_Min": 277,
		"keeper_90s": 3.1,
		"keeper_GA": 4,
		"keeper_GA90": 1.3,
		"keeper_SoTA": 15,
		"keeper_Saves": 12,
		"keeper_Save%": 80,
		"keeper_W": 0,
		"keeper_D": 1,
		"keeper_L": 2,
		"keeper_CS": 1,
		"keeper_CS%": 33.3,
		"keeper_PKatt": 1,
		"keeper_PKA": 1,
		"keeper_PKsv": 0,
		"keeper_PKm": 0,
		"keeper_Save%__1": 0,
		"keeper_Matches": "Matches",
		"code": "9970da54",
		"url": "/en/players/9970da54/Antonio-Sivera",
		"keeper_adv_Player": "Antonio Sivera\\9970da54",
		"keeper_adv_Nation": "es ESP",
		"keeper_adv_Pos": "GK",
		"keeper_adv_Squad": "Alavés",
		"keeper_adv_Age": 24,
		"keeper_adv_Born": 1996,
		"keeper_adv_90s": 3.1,
		"keeper_adv_GA": 4,
		"keeper_adv_PKA": 1,
		"keeper_adv_FK": 0,
		"keeper_adv_CK": 1,
		"keeper_adv_OG": 0,
		"keeper_adv_PSxG": 4.6,
		"keeper_adv_PSxG/SoT": 0.24,
		"keeper_adv_PSxG+/-": "+0.6",
		"keeper_adv_/90": "+0.19",
		"keeper_adv_Cmp": 32,
		"keeper_adv_Att": 75,
		"keeper_adv_Cmp%": 42.7,
		"keeper_adv_Att__1": 66,
		"keeper_adv_Thr": 7,
		"keeper_adv_Launch%": 69.7,
		"keeper_adv_AvgLen": 50.2,
		"keeper_adv_Att__2": 40,
		"keeper_adv_Launch%__1": 72.5,
		"keeper_adv_AvgLen__1": 56.3,
		"keeper_adv_Opp": 43,
		"keeper_adv_Stp": 6,
		"keeper_adv_Stp%": 14,
		"keeper_adv_#OPA": 2,
		"keeper_adv_#OPA/90": 0.65,
		"keeper_adv_AvgDist": 12.5,
		"keeper_adv_Matches": "Matches"
	},
	"42": {
		"keeper_Player": "David Soria\\8f8c6934",
		"keeper_Nation": "es ESP",
		"keeper_Pos": "GK",
		"keeper_Squad": "Getafe",
		"keeper_Age": 28,
		"keeper_Born": 1993,
		"keeper_MP": 38,
		"keeper_Starts": 38,
		"keeper_Min": 3414,
		"keeper_90s": 37.9,
		"keeper_GA": 41,
		"keeper_GA90": 1.08,
		"keeper_SoTA": 130,
		"keeper_Saves": 89,
		"keeper_Save%": 70,
		"keeper_W": 8,
		"keeper_D": 15,
		"keeper_L": 15,
		"keeper_CS": 14,
		"keeper_CS%": 36.8,
		"keeper_PKatt": 4,
		"keeper_PKA": 2,
		"keeper_PKsv": 1,
		"keeper_PKm": 1,
		"keeper_Save%__1": 33.3,
		"keeper_Matches": "Matches",
		"code": "8f8c6934",
		"url": "/en/players/8f8c6934/David-Soria",
		"keeper_adv_Player": "David Soria\\8f8c6934",
		"keeper_adv_Nation": "es ESP",
		"keeper_adv_Pos": "GK",
		"keeper_adv_Squad": "Getafe",
		"keeper_adv_Age": 28,
		"keeper_adv_Born": 1993,
		"keeper_adv_90s": 37.9,
		"keeper_adv_GA": 41,
		"keeper_adv_PKA": 2,
		"keeper_adv_FK": 0,
		"keeper_adv_CK": 5,
		"keeper_adv_OG": 1,
		"keeper_adv_PSxG": 37.8,
		"keeper_adv_PSxG/SoT": 0.27,
		"keeper_adv_PSxG+/-": -2.2,
		"keeper_adv_/90": -0.06,
		"keeper_adv_Cmp": 386,
		"keeper_adv_Att": 915,
		"keeper_adv_Cmp%": 42.2,
		"keeper_adv_Att__1": 889,
		"keeper_adv_Thr": 98,
		"keeper_adv_Launch%": 75.5,
		"keeper_adv_AvgLen": 52.9,
		"keeper_adv_Att__2": 291,
		"keeper_adv_Launch%__1": 83.8,
		"keeper_adv_AvgLen__1": 58.5,
		"keeper_adv_Opp": 363,
		"keeper_adv_Stp": 42,
		"keeper_adv_Stp%": 11.6,
		"keeper_adv_#OPA": 30,
		"keeper_adv_#OPA/90": 0.79,
		"keeper_adv_AvgDist": 14.4,
		"keeper_adv_Matches": "Matches"
	},
	"43": {
		"keeper_Player": "Marc-André ter Stegen\\6f51e382",
		"keeper_Nation": "de GER",
		"keeper_Pos": "GK",
		"keeper_Squad": "Barcelona",
		"keeper_Age": 29,
		"keeper_Born": 1992,
		"keeper_MP": 35,
		"keeper_Starts": 35,
		"keeper_Min": 3150,
		"keeper_90s": 35,
		"keeper_GA": 34,
		"keeper_GA90": 0.97,
		"keeper_SoTA": 110,
		"keeper_Saves": 78,
		"keeper_Save%": 70.9,
		"keeper_W": 19,
		"keeper_D": 9,
		"keeper_L": 7,
		"keeper_CS": 11,
		"keeper_CS%": 31.4,
		"keeper_PKatt": 3,
		"keeper_PKA": 2,
		"keeper_PKsv": 1,
		"keeper_PKm": 0,
		"keeper_Save%__1": 33.3,
		"keeper_Matches": "Matches",
		"code": "6f51e382",
		"url": "/en/players/6f51e382/Marc-Andre-ter-Stegen",
		"keeper_adv_Player": "Marc-André ter Stegen\\6f51e382",
		"keeper_adv_Nation": "de GER",
		"keeper_adv_Pos": "GK",
		"keeper_adv_Squad": "Barcelona",
		"keeper_adv_Age": 29,
		"keeper_adv_Born": 1992,
		"keeper_adv_90s": 35,
		"keeper_adv_GA": 34,
		"keeper_adv_PKA": 2,
		"keeper_adv_FK": 0,
		"keeper_adv_CK": 6,
		"keeper_adv_OG": 0,
		"keeper_adv_PSxG": 33.6,
		"keeper_adv_PSxG/SoT": 0.29,
		"keeper_adv_PSxG+/-": -0.4,
		"keeper_adv_/90": -0.01,
		"keeper_adv_Cmp": 211,
		"keeper_adv_Att": 355,
		"keeper_adv_Cmp%": 59.4,
		"keeper_adv_Att__1": 1076,
		"keeper_adv_Thr": 148,
		"keeper_adv_Launch%": 25.9,
		"keeper_adv_AvgLen": 29.8,
		"keeper_adv_Att__2": 204,
		"keeper_adv_Launch%__1": 37.3,
		"keeper_adv_AvgLen__1": 34.8,
		"keeper_adv_Opp": 216,
		"keeper_adv_Stp": 14,
		"keeper_adv_Stp%": 6.5,
		"keeper_adv_#OPA": 10,
		"keeper_adv_#OPA/90": 0.29,
		"keeper_adv_AvgDist": 13.2,
		"keeper_adv_Matches": "Matches"
	},
	"44": {
		"keeper_Player": "Rúben Vezo\\c67cd65c",
		"keeper_Nation": "pt POR",
		"keeper_Pos": "DF",
		"keeper_Squad": "Levante",
		"keeper_Age": 27,
		"keeper_Born": 1994,
		"keeper_MP": 1,
		"keeper_Starts": 1,
		"keeper_Min": 4,
		"keeper_90s": 26.9,
		"keeper_GA": 0,
		"keeper_GA90": 0,
		"keeper_SoTA": 0,
		"keeper_Saves": 0,
		"keeper_Save%": "",
		"keeper_W": 0,
		"keeper_D": 1,
		"keeper_L": 0,
		"keeper_CS": 0,
		"keeper_CS%": 0,
		"keeper_PKatt": 0,
		"keeper_PKA": 0,
		"keeper_PKsv": 0,
		"keeper_PKm": 0,
		"keeper_Save%__1": "",
		"keeper_Matches": "Matches",
		"code": "c67cd65c",
		"url": "/en/players/c67cd65c/Ruben-Vezo",
		"keeper_adv_Player": "Rúben Vezo\\c67cd65c",
		"keeper_adv_Nation": "pt POR",
		"keeper_adv_Pos": "DF",
		"keeper_adv_Squad": "Levante",
		"keeper_adv_Age": 27,
		"keeper_adv_Born": 1994,
		"keeper_adv_90s": 26.9,
		"keeper_adv_GA": 0,
		"keeper_adv_PKA": 0,
		"keeper_adv_FK": 0,
		"keeper_adv_CK": 0,
		"keeper_adv_OG": 0,
		"keeper_adv_PSxG": 0,
		"keeper_adv_PSxG/SoT": "",
		"keeper_adv_PSxG+/-": 0,
		"keeper_adv_/90": 0,
		"keeper_adv_Cmp": 2,
		"keeper_adv_Att": 4,
		"keeper_adv_Cmp%": 50,
		"keeper_adv_Att__1": 3,
		"keeper_adv_Thr": 0,
		"keeper_adv_Launch%": 100,
		"keeper_adv_AvgLen": 61.7,
		"keeper_adv_Att__2": 1,
		"keeper_adv_Launch%__1": 100,
		"keeper_adv_AvgLen__1": 64,
		"keeper_adv_Opp": 2,
		"keeper_adv_Stp": 0,
		"keeper_adv_Stp%": 0,
		"keeper_adv_#OPA": 0,
		"keeper_adv_#OPA/90": 0,
		"keeper_adv_AvgDist": "",
		"keeper_adv_Matches": "Matches"
	},
	"45": {
		"keeper_Player": "Luca Zidane\\c818c4d9",
		"keeper_Nation": "fr FRA",
		"keeper_Pos": "GKMF",
		"keeper_Squad": "Rayo Vallecano",
		"keeper_Age": 23,
		"keeper_Born": 1998,
		"keeper_MP": 8,
		"keeper_Starts": 8,
		"keeper_Min": 645,
		"keeper_90s": 7.2,
		"keeper_GA": 13,
		"keeper_GA90": 1.81,
		"keeper_SoTA": 37,
		"keeper_Saves": 24,
		"keeper_Save%": 64.9,
		"keeper_W": 0,
		"keeper_D": 1,
		"keeper_L": 7,
		"keeper_CS": 0,
		"keeper_CS%": 0,
		"keeper_PKatt": 0,
		"keeper_PKA": 0,
		"keeper_PKsv": 0,
		"keeper_PKm": 0,
		"keeper_Save%__1": "",
		"keeper_Matches": "Matches",
		"code": "c818c4d9",
		"url": "/en/players/c818c4d9/Luca-Zidane",
		"keeper_adv_Player": "Luca Zidane\\c818c4d9",
		"keeper_adv_Nation": "fr FRA",
		"keeper_adv_Pos": "GKMF",
		"keeper_adv_Squad": "Rayo Vallecano",
		"keeper_adv_Age": 23,
		"keeper_adv_Born": 1998,
		"keeper_adv_90s": 7.2,
		"keeper_adv_GA": 13,
		"keeper_adv_PKA": 0,
		"keeper_adv_FK": 0,
		"keeper_adv_CK": 1,
		"keeper_adv_OG": 0,
		"keeper_adv_PSxG": 12,
		"keeper_adv_PSxG/SoT": 0.32,
		"keeper_adv_PSxG+/-": -1,
		"keeper_adv_/90": -0.14,
		"keeper_adv_Cmp": 54,
		"keeper_adv_Att": 113,
		"keeper_adv_Cmp%": 47.8,
		"keeper_adv_Att__1": 178,
		"keeper_adv_Thr": 41,
		"keeper_adv_Launch%": 43.3,
		"keeper_adv_AvgLen": 38,
		"keeper_adv_Att__2": 53,
		"keeper_adv_Launch%__1": 67.9,
		"keeper_adv_AvgLen__1": 53.4,
		"keeper_adv_Opp": 54,
		"keeper_adv_Stp": 4,
		"keeper_adv_Stp%": 7.4,
		"keeper_adv_#OPA": 4,
		"keeper_adv_#OPA/90": 0.56,
		"keeper_adv_AvgDist": 12.6,
		"keeper_adv_Matches": "Matches"
	}
}